{
    "parent": "minecraft:item/generated",
    "textures": 
    {
      "layer0": "minecraft:item/amethyst_shard"
    },
    "overrides": [
        {"predicate":{"custom_model_data":982001},"model":"genesis:item/minerals/crystal_quartz"},
        {"predicate":{"custom_model_data":982002},"model":"genesis:item/minerals/mica"},
        {"predicate":{"custom_model_data":982003},"model":"genesis:item/minerals/malachite"},
        {"predicate":{"custom_model_data":982004},"model":"genesis:item/minerals/fluorite"},
        {"predicate":{"custom_model_data":982005},"model":"genesis:item/minerals/beryl"},
        {"predicate":{"custom_model_data":982006},"model":"genesis:item/minerals/garnet"},
        {"predicate":{"custom_model_data":982007},"model":"genesis:item/minerals/jasper"},
        {"predicate":{"custom_model_data":982008},"model":"genesis:item/minerals/topaz"},
        {"predicate":{"custom_model_data":982009},"model":"genesis:item/minerals/tourmaline"},
        {"predicate":{"custom_model_data":982010},"model":"genesis:item/minerals/mithril"},
        {"predicate":{"custom_model_data":982011},"model":"genesis:item/minerals/agate"},
        {"predicate":{"custom_model_data":982012},"model":"genesis:item/minerals/peridot"},
        {"predicate":{"custom_model_data":982013},"model":"genesis:item/minerals/zircon"},
        {"predicate":{"custom_model_data":982014},"model":"genesis:item/minerals/opal"},
        {"predicate":{"custom_model_data":982015},"model":"genesis:item/minerals/bedrock_mithril"},
        {"predicate":{"custom_model_data":982016},"model":"genesis:item/minerals/aquamarine"},
        {"predicate":{"custom_model_data":982017},"model":"genesis:item/minerals/ruby"},
        {"predicate":{"custom_model_data":982018},"model":"genesis:item/minerals/kunzite"},
        {"predicate":{"custom_model_data":982019},"model":"genesis:item/minerals/sapphire"},
        {"predicate":{"custom_model_data":982020},"model":"genesis:item/minerals/glacial_larimar"},
        {"predicate":{"custom_model_data":982021},"model":"genesis:item/minerals/fire_opal"},
        {"predicate":{"custom_model_data":982022},"model":"genesis:item/minerals/dragonscale_calcite"},
        {"predicate":{"custom_model_data":982023},"model":"genesis:item/minerals/black_opal"},
        {"predicate":{"custom_model_data":982024},"model":"genesis:item/minerals/umbra_heart"},
        {"predicate":{"custom_model_data":982025},"model":"genesis:item/minerals/azurite"},
        {"predicate":{"custom_model_data":982026},"model":"genesis:item/minerals/imperial_rosestone"},
        {"predicate":{"custom_model_data":982027},"model":"genesis:item/minerals/grape_agate"},
        {"predicate":{"custom_model_data":982028},"model":"genesis:item/minerals/seraphinite"}
    ]
}