{
"parent":"item/generated",
"textures":{
"layer0":"item/diamond_helmet"
},
"overrides":[
{"predicate":{"custom_model_data":53721},"model":"item/cod"},
{"predicate":{"custom_model_data":53722},"model":"item/egg"},
{"predicate":{"custom_model_data":53723},"model":"item/map"},
{"predicate":{"custom_model_data":53724},"model":"item/bow"},
{"predicate":{"custom_model_data":53725},"model":"item/ice"},
{"predicate":{"custom_model_data":53726},"model":"item/mud"},
{"predicate":{"custom_model_data":53727},"model":"item/tnt"},
{"predicate":{"custom_model_data":53728},"model":"item/beef"},
{"predicate":{"custom_model_data":53729},"model":"item/bell"},
{"predicate":{"custom_model_data":537210},"model":"item/coal"},
{"predicate":{"custom_model_data":537211},"model":"item/lead"},
{"predicate":{"custom_model_data":537212},"model":"item/bone"},
{"predicate":{"custom_model_data":537213},"model":"item/book"},
{"predicate":{"custom_model_data":537214},"model":"item/bowl"},
{"predicate":{"custom_model_data":537215},"model":"item/cake"},
{"predicate":{"custom_model_data":537216},"model":"item/clay"},
{"predicate":{"custom_model_data":537217},"model":"item/dirt"},
{"predicate":{"custom_model_data":537218},"model":"item/fern"},
{"predicate":{"custom_model_data":537219},"model":"item/kelp"},
{"predicate":{"custom_model_data":537220},"model":"item/loom"},
{"predicate":{"custom_model_data":537221},"model":"item/rail"},
{"predicate":{"custom_model_data":537222},"model":"item/sand"},
{"predicate":{"custom_model_data":537223},"model":"item/snow"},
{"predicate":{"custom_model_data":537224},"model":"item/tuff"},
{"predicate":{"custom_model_data":537225},"model":"item/vine"},
{"predicate":{"custom_model_data":537226},"model":"item/apple"},
{"predicate":{"custom_model_data":537227},"model":"item/arrow"},
{"predicate":{"custom_model_data":537228},"model":"item/anvil"},
{"predicate":{"custom_model_data":537229},"model":"item/clock"},
{"predicate":{"custom_model_data":537230},"model":"item/flint"},
{"predicate":{"custom_model_data":537231},"model":"item/paper"},
{"predicate":{"custom_model_data":537232},"model":"item/scute"},
{"predicate":{"custom_model_data":537233},"model":"item/bread"},
{"predicate":{"custom_model_data":537234},"model":"item/brick"},
{"predicate":{"custom_model_data":537235},"model":"item/brush"},
{"predicate":{"custom_model_data":537236},"model":"item/chain"},
{"predicate":{"custom_model_data":537237},"model":"item/chest"},
{"predicate":{"custom_model_data":537238},"model":"item/glass"},
{"predicate":{"custom_model_data":537239},"model":"item/grass"},
{"predicate":{"custom_model_data":537240},"model":"item/lever"},
{"predicate":{"custom_model_data":537241},"model":"item/light"},
{"predicate":{"custom_model_data":537242},"model":"item/lilac"},
{"predicate":{"custom_model_data":537243},"model":"item/melon"},
{"predicate":{"custom_model_data":537244},"model":"item/peony"},
{"predicate":{"custom_model_data":537245},"model":"item/poppy"},
{"predicate":{"custom_model_data":537246},"model":"item/sculk"},
{"predicate":{"custom_model_data":537247},"model":"item/stick"},
{"predicate":{"custom_model_data":537248},"model":"item/sugar"},
{"predicate":{"custom_model_data":537249},"model":"item/wheat"},
{"predicate":{"custom_model_data":537250},"model":"item/stone"},
{"predicate":{"custom_model_data":537251},"model":"item/torch"},
{"predicate":{"custom_model_data":537252},"model":"item/allium"},
{"predicate":{"custom_model_data":537253},"model":"item/azalea"},
{"predicate":{"custom_model_data":537254},"model":"item/bamboo"},
{"predicate":{"custom_model_data":537255},"model":"item/barrel"},
{"predicate":{"custom_model_data":537256},"model":"item/basalt"},
{"predicate":{"custom_model_data":537257},"model":"item/beacon"},
{"predicate":{"custom_model_data":537258},"model":"item/carrot"},
{"predicate":{"custom_model_data":537259},"model":"item/cookie"},
{"predicate":{"custom_model_data":537260},"model":"item/elytra"},
{"predicate":{"custom_model_data":537261},"model":"item/mutton"},
{"predicate":{"custom_model_data":537262},"model":"item/potato"},
{"predicate":{"custom_model_data":537263},"model":"item/potion"},
{"predicate":{"custom_model_data":537264},"model":"item/quartz"},
{"predicate":{"custom_model_data":537265},"model":"item/rabbit"},
{"predicate":{"custom_model_data":537266},"model":"item/saddle"},
{"predicate":{"custom_model_data":537267},"model":"item/salmon"},
{"predicate":{"custom_model_data":537268},"model":"item/bricks"},
{"predicate":{"custom_model_data":537269},"model":"item/bucket"},
{"predicate":{"custom_model_data":537270},"model":"item/bundle"},
{"predicate":{"custom_model_data":537271},"model":"item/cactus"},
{"predicate":{"custom_model_data":537272},"model":"item/candle"},
{"predicate":{"custom_model_data":537273},"model":"item/cobweb"},
{"predicate":{"custom_model_data":537274},"model":"item/gravel"},
{"predicate":{"custom_model_data":537275},"model":"item/hopper"},
{"predicate":{"custom_model_data":537276},"model":"item/jigsaw"},
{"predicate":{"custom_model_data":537277},"model":"item/ladder"},
{"predicate":{"custom_model_data":537278},"model":"item/piston"},
{"predicate":{"custom_model_data":537279},"model":"item/podzol"},
{"predicate":{"custom_model_data":537280},"model":"item/shears"},
{"predicate":{"custom_model_data":537281},"model":"item/shield"},
{"predicate":{"custom_model_data":537282},"model":"item/smoker"},
{"predicate":{"custom_model_data":537283},"model":"item/sponge"},
{"predicate":{"custom_model_data":537284},"model":"item/string"},
{"predicate":{"custom_model_data":537285},"model":"item/target"},
{"predicate":{"custom_model_data":537286},"model":"item/barrier"},
{"predicate":{"custom_model_data":537287},"model":"item/bedrock"},
{"predicate":{"custom_model_data":537288},"model":"item/beehive"},
{"predicate":{"custom_model_data":537289},"model":"item/compass"},
{"predicate":{"custom_model_data":537290},"model":"item/feather"},
{"predicate":{"custom_model_data":537291},"model":"item/ink_sac"},
{"predicate":{"custom_model_data":537292},"model":"item/leather"},
{"predicate":{"custom_model_data":537293},"model":"item/red_dye"},
{"predicate":{"custom_model_data":537294},"model":"item/calcite"},
{"predicate":{"custom_model_data":537295},"model":"item/chicken"},
{"predicate":{"custom_model_data":537296},"model":"item/conduit"},
{"predicate":{"custom_model_data":537297},"model":"item/diamond"},
{"predicate":{"custom_model_data":537298},"model":"item/diorite"},
{"predicate":{"custom_model_data":537299},"model":"item/dropper"},
{"predicate":{"custom_model_data":5372100},"model":"item/emerald"},
{"predicate":{"custom_model_data":5372101},"model":"item/end_rod"},
{"predicate":{"custom_model_data":5372102},"model":"item/furnace"},
{"predicate":{"custom_model_data":5372103},"model":"item/granite"},
{"predicate":{"custom_model_data":5372104},"model":"item/jukebox"},
{"predicate":{"custom_model_data":5372105},"model":"item/lantern"},
{"predicate":{"custom_model_data":5372106},"model":"item/lectern"},
{"predicate":{"custom_model_data":5372107},"model":"item/oak_log"},
{"predicate":{"custom_model_data":5372108},"model":"item/pumpkin"},
{"predicate":{"custom_model_data":5372109},"model":"item/red_bed"},
{"predicate":{"custom_model_data":5372110},"model":"item/trident"},
{"predicate":{"custom_model_data":5372111},"model":"item/spawner"},
{"predicate":{"custom_model_data":5372112},"model":"item/beetroot"},
{"predicate":{"custom_model_data":5372113},"model":"item/andesite"},
{"predicate":{"custom_model_data":5372114},"model":"item/bee_nest"},
{"predicate":{"custom_model_data":5372115},"model":"item/blue_dye"},
{"predicate":{"custom_model_data":5372116},"model":"item/cyan_dye"},
{"predicate":{"custom_model_data":5372117},"model":"item/gray_dye"},
{"predicate":{"custom_model_data":5372118},"model":"item/iron_axe"},
{"predicate":{"custom_model_data":5372119},"model":"item/iron_hoe"},
{"predicate":{"custom_model_data":5372120},"model":"item/lime_dye"},
{"predicate":{"custom_model_data":5372121},"model":"item/minecart"},
{"predicate":{"custom_model_data":5372122},"model":"item/name_tag"},
{"predicate":{"custom_model_data":5372123},"model":"item/oak_boat"},
{"predicate":{"custom_model_data":5372124},"model":"item/painting"},
{"predicate":{"custom_model_data":5372125},"model":"item/pink_dye"},
{"predicate":{"custom_model_data":5372126},"model":"item/porkchop"},
{"predicate":{"custom_model_data":5372127},"model":"item/raw_gold"},
{"predicate":{"custom_model_data":5372128},"model":"item/raw_iron"},
{"predicate":{"custom_model_data":5372129},"model":"item/blue_bed"},
{"predicate":{"custom_model_data":5372130},"model":"item/blue_ice"},
{"predicate":{"custom_model_data":5372131},"model":"item/campfire"},
{"predicate":{"custom_model_data":5372132},"model":"item/cauldron"},
{"predicate":{"custom_model_data":5372133},"model":"item/coal_ore"},
{"predicate":{"custom_model_data":5372134},"model":"item/crossbow"},
{"predicate":{"custom_model_data":5372135},"model":"item/cyan_bed"},
{"predicate":{"custom_model_data":5372136},"model":"item/farmland"},
{"predicate":{"custom_model_data":5372137},"model":"item/gold_ore"},
{"predicate":{"custom_model_data":5372138},"model":"item/gray_bed"},
{"predicate":{"custom_model_data":5372139},"model":"item/iron_ore"},
{"predicate":{"custom_model_data":5372140},"model":"item/lily_pad"},
{"predicate":{"custom_model_data":5372141},"model":"item/lime_bed"},
{"predicate":{"custom_model_data":5372142},"model":"item/mycelium"},
{"predicate":{"custom_model_data":5372143},"model":"item/oak_door"},
{"predicate":{"custom_model_data":5372144},"model":"item/oak_sign"},
{"predicate":{"custom_model_data":5372145},"model":"item/oak_slab"},
{"predicate":{"custom_model_data":5372146},"model":"item/oak_wood"},
{"predicate":{"custom_model_data":5372147},"model":"item/observer"},
{"predicate":{"custom_model_data":5372148},"model":"item/obsidian"},
{"predicate":{"custom_model_data":5372149},"model":"item/pink_bed"},
{"predicate":{"custom_model_data":5372150},"model":"item/red_sand"},
{"predicate":{"custom_model_data":5372151},"model":"item/red_wool"},
{"predicate":{"custom_model_data":5372152},"model":"item/redstone"},
{"predicate":{"custom_model_data":5372153},"model":"item/repeater"},
{"predicate":{"custom_model_data":5372154},"model":"item/seagrass"},
{"predicate":{"custom_model_data":5372155},"model":"item/snowball"},
{"predicate":{"custom_model_data":5372156},"model":"item/spyglass"},
{"predicate":{"custom_model_data":5372157},"model":"item/black_dye"},
{"predicate":{"custom_model_data":5372158},"model":"item/birch_log"},
{"predicate":{"custom_model_data":5372159},"model":"item/black_bed"},
{"predicate":{"custom_model_data":5372160},"model":"item/charcoal"},
{"predicate":{"custom_model_data":5372161},"model":"item/blaze_rod"},
{"predicate":{"custom_model_data":5372162},"model":"item/clay_ball"},
{"predicate":{"custom_model_data":5372163},"model":"item/ender_eye"},
{"predicate":{"custom_model_data":5372164},"model":"item/goat_horn"},
{"predicate":{"custom_model_data":5372165},"model":"item/green_dye"},
{"predicate":{"custom_model_data":5372166},"model":"item/gunpowder"},
{"predicate":{"custom_model_data":5372167},"model":"item/blue_wool"},
{"predicate":{"custom_model_data":5372168},"model":"item/bone_meal"},
{"predicate":{"custom_model_data":5372169},"model":"item/bookshelf"},
{"predicate":{"custom_model_data":5372170},"model":"item/brown_bed"},
{"predicate":{"custom_model_data":5372171},"model":"item/brown_dye"},
{"predicate":{"custom_model_data":5372172},"model":"item/composter"},
{"predicate":{"custom_model_data":5372173},"model":"item/cyan_wool"},
{"predicate":{"custom_model_data":5372174},"model":"item/dandelion"},
{"predicate":{"custom_model_data":5372175},"model":"item/dead_bush"},
{"predicate":{"custom_model_data":5372176},"model":"item/deepslate"},
{"predicate":{"custom_model_data":5372177},"model":"item/dirt_path"},
{"predicate":{"custom_model_data":5372178},"model":"item/dispenser"},
{"predicate":{"custom_model_data":5372179},"model":"item/end_stone"},
{"predicate":{"custom_model_data":5372180},"model":"item/frogspawn"},
{"predicate":{"custom_model_data":5372181},"model":"item/glowstone"},
{"predicate":{"custom_model_data":5372182},"model":"item/gray_wool"},
{"predicate":{"custom_model_data":5372183},"model":"item/green_bed"},
{"predicate":{"custom_model_data":5372184},"model":"item/hay_block"},
{"predicate":{"custom_model_data":5372185},"model":"item/honeycomb"},
{"predicate":{"custom_model_data":5372186},"model":"item/iron_bars"},
{"predicate":{"custom_model_data":5372187},"model":"item/iron_door"},
{"predicate":{"custom_model_data":5372188},"model":"item/lapis_ore"},
{"predicate":{"custom_model_data":5372189},"model":"item/lime_wool"},
{"predicate":{"custom_model_data":5372190},"model":"item/lodestone"},
{"predicate":{"custom_model_data":5372191},"model":"item/oak_fence"},
{"predicate":{"custom_model_data":5372192},"model":"item/pink_wool"},
{"predicate":{"custom_model_data":5372193},"model":"item/red_tulip"},
{"predicate":{"custom_model_data":5372194},"model":"item/rose_bush"},
{"predicate":{"custom_model_data":5372195},"model":"item/sandstone"},
{"predicate":{"custom_model_data":5372196},"model":"item/stone_axe"},
{"predicate":{"custom_model_data":5372197},"model":"item/stone_hoe"},
{"predicate":{"custom_model_data":5372198},"model":"item/white_dye"},
{"predicate":{"custom_model_data":5372199},"model":"item/soul_sand"},
{"predicate":{"custom_model_data":5372200},"model":"item/soul_soil"},
{"predicate":{"custom_model_data":5372201},"model":"item/sunflower"},
{"predicate":{"custom_model_data":5372202},"model":"item/white_bed"},
{"predicate":{"custom_model_data":5372203},"model":"item/acacia_log"},
{"predicate":{"custom_model_data":5372204},"model":"item/birch_boat"},
{"predicate":{"custom_model_data":5372205},"model":"item/birch_door"},
{"predicate":{"custom_model_data":5372206},"model":"item/birch_sign"},
{"predicate":{"custom_model_data":5372207},"model":"item/birch_slab"},
{"predicate":{"custom_model_data":5372208},"model":"item/birch_wood"},
{"predicate":{"custom_model_data":5372209},"model":"item/cod_bucket"},
{"predicate":{"custom_model_data":5372210},"model":"item/cooked_cod"},
{"predicate":{"custom_model_data":5372211},"model":"item/dried_kelp"},
{"predicate":{"custom_model_data":5372212},"model":"item/echo_shard"},
{"predicate":{"custom_model_data":5372213},"model":"item/ghast_tear"},
{"predicate":{"custom_model_data":5372214},"model":"item/gold_ingot"},
{"predicate":{"custom_model_data":5372215},"model":"item/golden_axe"},
{"predicate":{"custom_model_data":5372216},"model":"item/golden_hoe"},
{"predicate":{"custom_model_data":5372217},"model":"item/iron_boots"},
{"predicate":{"custom_model_data":5372218},"model":"item/iron_ingot"},
{"predicate":{"custom_model_data":5372219},"model":"item/iron_sword"},
{"predicate":{"custom_model_data":5372220},"model":"item/item_frame"},
{"predicate":{"custom_model_data":5372221},"model":"item/orange_dye"},
{"predicate":{"custom_model_data":5372222},"model":"item/pufferfish"},
{"predicate":{"custom_model_data":5372223},"model":"item/purple_dye"},
{"predicate":{"custom_model_data":5372224},"model":"item/raw_copper"},
{"predicate":{"custom_model_data":5372225},"model":"item/black_wool"},
{"predicate":{"custom_model_data":5372226},"model":"item/blackstone"},
{"predicate":{"custom_model_data":5372227},"model":"item/bone_block"},
{"predicate":{"custom_model_data":5372228},"model":"item/brick_slab"},
{"predicate":{"custom_model_data":5372229},"model":"item/brick_wall"},
{"predicate":{"custom_model_data":5372230},"model":"item/brown_wool"},
{"predicate":{"custom_model_data":5372231},"model":"item/cherry_log"},
{"predicate":{"custom_model_data":5372232},"model":"item/coal_block"},
{"predicate":{"custom_model_data":5372233},"model":"item/comparator"},
{"predicate":{"custom_model_data":5372234},"model":"item/copper_ore"},
{"predicate":{"custom_model_data":5372235},"model":"item/cornflower"},
{"predicate":{"custom_model_data":5372236},"model":"item/cut_copper"},
{"predicate":{"custom_model_data":5372237},"model":"item/dragon_egg"},
{"predicate":{"custom_model_data":5372238},"model":"item/filled_map"},
{"predicate":{"custom_model_data":5372239},"model":"item/fire_coral"},
{"predicate":{"custom_model_data":5372240},"model":"item/flower_pot"},
{"predicate":{"custom_model_data":5372241},"model":"item/glass_pane"},
{"predicate":{"custom_model_data":5372242},"model":"item/gold_block"},
{"predicate":{"custom_model_data":5372243},"model":"item/green_wool"},
{"predicate":{"custom_model_data":5372244},"model":"item/grindstone"},
{"predicate":{"custom_model_data":5372245},"model":"item/horn_coral"},
{"predicate":{"custom_model_data":5372246},"model":"item/iron_block"},
{"predicate":{"custom_model_data":5372247},"model":"item/jungle_log"},
{"predicate":{"custom_model_data":5372248},"model":"item/large_fern"},
{"predicate":{"custom_model_data":5372249},"model":"item/moss_block"},
{"predicate":{"custom_model_data":5372250},"model":"item/mud_bricks"},
{"predicate":{"custom_model_data":5372251},"model":"item/netherrack"},
{"predicate":{"custom_model_data":5372252},"model":"item/note_block"},
{"predicate":{"custom_model_data":5372253},"model":"item/oak_button"},
{"predicate":{"custom_model_data":5372254},"model":"item/oak_leaves"},
{"predicate":{"custom_model_data":5372255},"model":"item/oak_planks"},
{"predicate":{"custom_model_data":5372256},"model":"item/oak_stairs"},
{"predicate":{"custom_model_data":5372257},"model":"item/orange_bed"},
{"predicate":{"custom_model_data":5372258},"model":"item/packed_ice"},
{"predicate":{"custom_model_data":5372259},"model":"item/packed_mud"},
{"predicate":{"custom_model_data":5372260},"model":"item/pink_tulip"},
{"predicate":{"custom_model_data":5372261},"model":"item/prismarine"},
{"predicate":{"custom_model_data":5372262},"model":"item/purple_bed"},
{"predicate":{"custom_model_data":5372263},"model":"item/red_banner"},
{"predicate":{"custom_model_data":5372264},"model":"item/red_candle"},
{"predicate":{"custom_model_data":5372265},"model":"item/red_carpet"},
{"predicate":{"custom_model_data":5372266},"model":"item/sculk_vein"},
{"predicate":{"custom_model_data":5372267},"model":"item/sea_pickle"},
{"predicate":{"custom_model_data":5372268},"model":"item/slime_ball"},
{"predicate":{"custom_model_data":5372269},"model":"item/spider_eye"},
{"predicate":{"custom_model_data":5372270},"model":"item/wooden_axe"},
{"predicate":{"custom_model_data":5372271},"model":"item/wooden_hoe"},
{"predicate":{"custom_model_data":5372272},"model":"item/yellow_dye"},
{"predicate":{"custom_model_data":5372273},"model":"item/snow_block"},
{"predicate":{"custom_model_data":5372274},"model":"item/soul_torch"},
{"predicate":{"custom_model_data":5372275},"model":"item/spruce_log"},
{"predicate":{"custom_model_data":5372276},"model":"item/stone_slab"},
{"predicate":{"custom_model_data":5372277},"model":"item/sugar_cane"},
{"predicate":{"custom_model_data":5372278},"model":"item/tall_grass"},
{"predicate":{"custom_model_data":5372279},"model":"item/terracotta"},
{"predicate":{"custom_model_data":5372280},"model":"item/tube_coral"},
{"predicate":{"custom_model_data":5372281},"model":"item/turtle_egg"},
{"predicate":{"custom_model_data":5372282},"model":"item/wet_sponge"},
{"predicate":{"custom_model_data":5372283},"model":"item/white_wool"},
{"predicate":{"custom_model_data":5372284},"model":"item/yellow_bed"},
{"predicate":{"custom_model_data":5372285},"model":"item/acacia_boat"},
{"predicate":{"custom_model_data":5372286},"model":"item/acacia_door"},
{"predicate":{"custom_model_data":5372287},"model":"item/armor_stand"},
{"predicate":{"custom_model_data":5372288},"model":"item/bamboo_raft"},
{"predicate":{"custom_model_data":5372289},"model":"item/acacia_sign"},
{"predicate":{"custom_model_data":5372290},"model":"item/acacia_slab"},
{"predicate":{"custom_model_data":5372291},"model":"item/acacia_wood"},
{"predicate":{"custom_model_data":5372292},"model":"item/azure_bluet"},
{"predicate":{"custom_model_data":5372293},"model":"item/bamboo_door"},
{"predicate":{"custom_model_data":5372294},"model":"item/bamboo_sign"},
{"predicate":{"custom_model_data":5372295},"model":"item/bamboo_slab"},
{"predicate":{"custom_model_data":5372296},"model":"item/birch_fence"},
{"predicate":{"custom_model_data":5372297},"model":"item/cherry_boat"},
{"predicate":{"custom_model_data":5372298},"model":"item/cocoa_beans"},
{"predicate":{"custom_model_data":5372299},"model":"item/cooked_beef"},
{"predicate":{"custom_model_data":5372300},"model":"item/debug_stick"},
{"predicate":{"custom_model_data":5372301},"model":"item/end_crystal"},
{"predicate":{"custom_model_data":5372302},"model":"item/ender_pearl"},
{"predicate":{"custom_model_data":5372303},"model":"item/fishing_rod"},
{"predicate":{"custom_model_data":5372304},"model":"item/gold_nugget"},
{"predicate":{"custom_model_data":5372305},"model":"item/iron_helmet"},
{"predicate":{"custom_model_data":5372306},"model":"item/iron_nugget"},
{"predicate":{"custom_model_data":5372307},"model":"item/iron_shovel"},
{"predicate":{"custom_model_data":5372308},"model":"item/jungle_boat"},
{"predicate":{"custom_model_data":5372309},"model":"item/lava_bucket"},
{"predicate":{"custom_model_data":5372310},"model":"item/magenta_dye"},
{"predicate":{"custom_model_data":5372311},"model":"item/magma_cream"},
{"predicate":{"custom_model_data":5372312},"model":"item/melon_seeds"},
{"predicate":{"custom_model_data":5372313},"model":"item/melon_slice"},
{"predicate":{"custom_model_data":5372314},"model":"item/milk_bucket"},
{"predicate":{"custom_model_data":5372315},"model":"item/pitcher_pod"},
{"predicate":{"custom_model_data":5372316},"model":"item/pumpkin_pie"},
{"predicate":{"custom_model_data":5372317},"model":"item/rabbit_foot"},
{"predicate":{"custom_model_data":5372318},"model":"item/rabbit_hide"},
{"predicate":{"custom_model_data":5372319},"model":"item/rabbit_stew"},
{"predicate":{"custom_model_data":5372320},"model":"item/blue_banner"},
{"predicate":{"custom_model_data":5372321},"model":"item/blue_candle"},
{"predicate":{"custom_model_data":5372322},"model":"item/blue_carpet"},
{"predicate":{"custom_model_data":5372323},"model":"item/blue_orchid"},
{"predicate":{"custom_model_data":5372324},"model":"item/brain_coral"},
{"predicate":{"custom_model_data":5372325},"model":"item/cherry_door"},
{"predicate":{"custom_model_data":5372326},"model":"item/cherry_sign"},
{"predicate":{"custom_model_data":5372327},"model":"item/cherry_slab"},
{"predicate":{"custom_model_data":5372328},"model":"item/cherry_wood"},
{"predicate":{"custom_model_data":5372329},"model":"item/coarse_dirt"},
{"predicate":{"custom_model_data":5372330},"model":"item/cobblestone"},
{"predicate":{"custom_model_data":5372331},"model":"item/cyan_banner"},
{"predicate":{"custom_model_data":5372332},"model":"item/cyan_candle"},
{"predicate":{"custom_model_data":5372333},"model":"item/cyan_carpet"},
{"predicate":{"custom_model_data":5372334},"model":"item/diamond_axe"},
{"predicate":{"custom_model_data":5372335},"model":"item/diamond_hoe"},
{"predicate":{"custom_model_data":5372336},"model":"item/diamond_ore"},
{"predicate":{"custom_model_data":5372337},"model":"item/dragon_head"},
{"predicate":{"custom_model_data":5372338},"model":"item/emerald_ore"},
{"predicate":{"custom_model_data":5372339},"model":"item/ender_chest"},
{"predicate":{"custom_model_data":5372340},"model":"item/fire_charge"},
{"predicate":{"custom_model_data":5372341},"model":"item/glow_lichen"},
{"predicate":{"custom_model_data":5372342},"model":"item/grass_block"},
{"predicate":{"custom_model_data":5372343},"model":"item/gray_banner"},
{"predicate":{"custom_model_data":5372344},"model":"item/gray_candle"},
{"predicate":{"custom_model_data":5372345},"model":"item/gray_carpet"},
{"predicate":{"custom_model_data":5372346},"model":"item/honey_block"},
{"predicate":{"custom_model_data":5372347},"model":"item/jungle_door"},
{"predicate":{"custom_model_data":5372348},"model":"item/jungle_sign"},
{"predicate":{"custom_model_data":5372349},"model":"item/jungle_slab"},
{"predicate":{"custom_model_data":5372350},"model":"item/jungle_wood"},
{"predicate":{"custom_model_data":5372351},"model":"item/lapis_block"},
{"predicate":{"custom_model_data":5372352},"model":"item/lime_banner"},
{"predicate":{"custom_model_data":5372353},"model":"item/lime_candle"},
{"predicate":{"custom_model_data":5372354},"model":"item/lime_carpet"},
{"predicate":{"custom_model_data":5372355},"model":"item/magenta_bed"},
{"predicate":{"custom_model_data":5372356},"model":"item/magma_block"},
{"predicate":{"custom_model_data":5372357},"model":"item/moss_carpet"},
{"predicate":{"custom_model_data":5372358},"model":"item/nether_star"},
{"predicate":{"custom_model_data":5372359},"model":"item/nether_wart"},
{"predicate":{"custom_model_data":5372360},"model":"item/oak_sapling"},
{"predicate":{"custom_model_data":5372361},"model":"item/orange_wool"},
{"predicate":{"custom_model_data":5372362},"model":"item/oxeye_daisy"},
{"predicate":{"custom_model_data":5372363},"model":"item/piglin_head"},
{"predicate":{"custom_model_data":5372364},"model":"item/pink_banner"},
{"predicate":{"custom_model_data":5372365},"model":"item/pink_candle"},
{"predicate":{"custom_model_data":5372366},"model":"item/pink_carpet"},
{"predicate":{"custom_model_data":5372367},"model":"item/pink_petals"},
{"predicate":{"custom_model_data":5372368},"model":"item/player_head"},
{"predicate":{"custom_model_data":5372369},"model":"item/purple_wool"},
{"predicate":{"custom_model_data":5372370},"model":"item/purpur_slab"},
{"predicate":{"custom_model_data":5372371},"model":"item/quartz_slab"},
{"predicate":{"custom_model_data":5372372},"model":"item/rooted_dirt"},
{"predicate":{"custom_model_data":5372373},"model":"item/scaffolding"},
{"predicate":{"custom_model_data":5372374},"model":"item/sea_lantern"},
{"predicate":{"custom_model_data":5372375},"model":"item/spruce_boat"},
{"predicate":{"custom_model_data":5372376},"model":"item/stone_sword"},
{"predicate":{"custom_model_data":5372377},"model":"item/wheat_seeds"},
{"predicate":{"custom_model_data":5372378},"model":"item/shroomlight"},
{"predicate":{"custom_model_data":5372379},"model":"item/shulker_box"},
{"predicate":{"custom_model_data":5372380},"model":"item/slime_block"},
{"predicate":{"custom_model_data":5372381},"model":"item/sniffer_egg"},
{"predicate":{"custom_model_data":5372382},"model":"item/spruce_door"},
{"predicate":{"custom_model_data":5372383},"model":"item/spruce_sign"},
{"predicate":{"custom_model_data":5372384},"model":"item/spruce_slab"},
{"predicate":{"custom_model_data":5372385},"model":"item/spruce_wood"},
{"predicate":{"custom_model_data":5372386},"model":"item/stonecutter"},
{"predicate":{"custom_model_data":5372387},"model":"item/torchflower"},
{"predicate":{"custom_model_data":5372388},"model":"item/warped_door"},
{"predicate":{"custom_model_data":5372389},"model":"item/warped_sign"},
{"predicate":{"custom_model_data":5372390},"model":"item/warped_slab"},
{"predicate":{"custom_model_data":5372391},"model":"item/warped_stem"},
{"predicate":{"custom_model_data":5372392},"model":"item/white_tulip"},
{"predicate":{"custom_model_data":5372393},"model":"item/wither_rose"},
{"predicate":{"custom_model_data":5372394},"model":"item/yellow_wool"},
{"predicate":{"custom_model_data":5372395},"model":"item/zombie_head"},
{"predicate":{"custom_model_data":5372396},"model":"item/acacia_fence"},
{"predicate":{"custom_model_data":5372397},"model":"item/baked_potato"},
{"predicate":{"custom_model_data":5372398},"model":"item/bamboo_block"},
{"predicate":{"custom_model_data":5372399},"model":"item/bamboo_fence"},
{"predicate":{"custom_model_data":5372400},"model":"item/big_dripleaf"},
{"predicate":{"custom_model_data":5372401},"model":"item/birch_button"},
{"predicate":{"custom_model_data":5372402},"model":"item/birch_leaves"},
{"predicate":{"custom_model_data":5372403},"model":"item/birch_planks"},
{"predicate":{"custom_model_data":5372404},"model":"item/birch_stairs"},
{"predicate":{"custom_model_data":5372405},"model":"item/black_banner"},
{"predicate":{"custom_model_data":5372406},"model":"item/black_candle"},
{"predicate":{"custom_model_data":5372407},"model":"item/black_carpet"},
{"predicate":{"custom_model_data":5372408},"model":"item/blaze_powder"},
{"predicate":{"custom_model_data":5372409},"model":"item/chorus_fruit"},
{"predicate":{"custom_model_data":5372410},"model":"item/glass_bottle"},
{"predicate":{"custom_model_data":5372411},"model":"item/glow_berries"},
{"predicate":{"custom_model_data":5372412},"model":"item/glow_ink_sac"},
{"predicate":{"custom_model_data":5372413},"model":"item/golden_apple"},
{"predicate":{"custom_model_data":5372414},"model":"item/golden_boots"},
{"predicate":{"custom_model_data":5372415},"model":"item/golden_sword"},
{"predicate":{"custom_model_data":5372416},"model":"item/honey_bottle"},
{"predicate":{"custom_model_data":5372417},"model":"item/iron_pickaxe"},
{"predicate":{"custom_model_data":5372418},"model":"item/lapis_lazuli"},
{"predicate":{"custom_model_data":5372419},"model":"item/music_disc_5"},
{"predicate":{"custom_model_data":5372420},"model":"item/nether_brick"},
{"predicate":{"custom_model_data":5372421},"model":"item/rotten_flesh"},
{"predicate":{"custom_model_data":5372422},"model":"item/brick_stairs"},
{"predicate":{"custom_model_data":5372423},"model":"item/brown_banner"},
{"predicate":{"custom_model_data":5372424},"model":"item/brown_candle"},
{"predicate":{"custom_model_data":5372425},"model":"item/brown_carpet"},
{"predicate":{"custom_model_data":5372426},"model":"item/bubble_coral"},
{"predicate":{"custom_model_data":5372427},"model":"item/cherry_fence"},
{"predicate":{"custom_model_data":5372428},"model":"item/chorus_plant"},
{"predicate":{"custom_model_data":5372429},"model":"item/copper_block"},
{"predicate":{"custom_model_data":5372430},"model":"item/copper_ingot"},
{"predicate":{"custom_model_data":5372431},"model":"item/creeper_head"},
{"predicate":{"custom_model_data":5372432},"model":"item/crimson_door"},
{"predicate":{"custom_model_data":5372433},"model":"item/crimson_sign"},
{"predicate":{"custom_model_data":5372434},"model":"item/crimson_slab"},
{"predicate":{"custom_model_data":5372435},"model":"item/crimson_stem"},
{"predicate":{"custom_model_data":5372436},"model":"item/dark_oak_log"},
{"predicate":{"custom_model_data":5372437},"model":"item/diorite_slab"},
{"predicate":{"custom_model_data":5372438},"model":"item/diorite_wall"},
{"predicate":{"custom_model_data":5372439},"model":"item/granite_slab"},
{"predicate":{"custom_model_data":5372440},"model":"item/granite_wall"},
{"predicate":{"custom_model_data":5372441},"model":"item/green_banner"},
{"predicate":{"custom_model_data":5372442},"model":"item/green_candle"},
{"predicate":{"custom_model_data":5372443},"model":"item/green_carpet"},
{"predicate":{"custom_model_data":5372444},"model":"item/jungle_fence"},
{"predicate":{"custom_model_data":5372445},"model":"item/magenta_wool"},
{"predicate":{"custom_model_data":5372446},"model":"item/mangrove_log"},
{"predicate":{"custom_model_data":5372447},"model":"item/oak_trapdoor"},
{"predicate":{"custom_model_data":5372448},"model":"item/orange_tulip"},
{"predicate":{"custom_model_data":5372449},"model":"item/powered_rail"},
{"predicate":{"custom_model_data":5372450},"model":"item/purpur_block"},
{"predicate":{"custom_model_data":5372451},"model":"item/quartz_block"},
{"predicate":{"custom_model_data":5372452},"model":"item/red_concrete"},
{"predicate":{"custom_model_data":5372453},"model":"item/red_mushroom"},
{"predicate":{"custom_model_data":5372454},"model":"item/redstone_ore"},
{"predicate":{"custom_model_data":5372455},"model":"item/sculk_sensor"},
{"predicate":{"custom_model_data":5372456},"model":"item/stone_shovel"},
{"predicate":{"custom_model_data":5372457},"model":"item/tipped_arrow"},
{"predicate":{"custom_model_data":5372458},"model":"item/tnt_minecart"},
{"predicate":{"custom_model_data":5372459},"model":"item/water_bucket"},
{"predicate":{"custom_model_data":5372460},"model":"item/wooden_sword"},
{"predicate":{"custom_model_data":5372461},"model":"item/written_book"},
{"predicate":{"custom_model_data":5372462},"model":"item/smooth_stone"},
{"predicate":{"custom_model_data":5372463},"model":"item/soul_lantern"},
{"predicate":{"custom_model_data":5372464},"model":"item/spruce_fence"},
{"predicate":{"custom_model_data":5372465},"model":"item/stone_bricks"},
{"predicate":{"custom_model_data":5372466},"model":"item/stone_button"},
{"predicate":{"custom_model_data":5372467},"model":"item/stone_stairs"},
{"predicate":{"custom_model_data":5372468},"model":"item/tinted_glass"},
{"predicate":{"custom_model_data":5372469},"model":"item/warped_fence"},
{"predicate":{"custom_model_data":5372470},"model":"item/warped_roots"},
{"predicate":{"custom_model_data":5372471},"model":"item/white_banner"},
{"predicate":{"custom_model_data":5372472},"model":"item/white_candle"},
{"predicate":{"custom_model_data":5372473},"model":"item/white_carpet"},
{"predicate":{"custom_model_data":5372474},"model":"item/acacia_button"},
{"predicate":{"custom_model_data":5372475},"model":"item/acacia_leaves"},
{"predicate":{"custom_model_data":5372476},"model":"item/bat_spawn_egg"},
{"predicate":{"custom_model_data":5372477},"model":"item/bee_spawn_egg"},
{"predicate":{"custom_model_data":5372478},"model":"item/beetroot_soup"},
{"predicate":{"custom_model_data":5372479},"model":"item/acacia_planks"},
{"predicate":{"custom_model_data":5372480},"model":"item/acacia_stairs"},
{"predicate":{"custom_model_data":5372481},"model":"item/andesite_slab"},
{"predicate":{"custom_model_data":5372482},"model":"item/andesite_wall"},
{"predicate":{"custom_model_data":5372483},"model":"item/azalea_leaves"},
{"predicate":{"custom_model_data":5372484},"model":"item/bamboo_button"},
{"predicate":{"custom_model_data":5372485},"model":"item/bamboo_mosaic"},
{"predicate":{"custom_model_data":5372486},"model":"item/bamboo_planks"},
{"predicate":{"custom_model_data":5372487},"model":"item/bamboo_stairs"},
{"predicate":{"custom_model_data":5372488},"model":"item/birch_sapling"},
{"predicate":{"custom_model_data":5372489},"model":"item/cat_spawn_egg"},
{"predicate":{"custom_model_data":5372490},"model":"item/cooked_mutton"},
{"predicate":{"custom_model_data":5372491},"model":"item/cooked_rabbit"},
{"predicate":{"custom_model_data":5372492},"model":"item/cooked_salmon"},
{"predicate":{"custom_model_data":5372493},"model":"item/dark_oak_boat"},
{"predicate":{"custom_model_data":5372494},"model":"item/dragon_breath"},
{"predicate":{"custom_model_data":5372495},"model":"item/firework_star"},
{"predicate":{"custom_model_data":5372496},"model":"item/fox_spawn_egg"},
{"predicate":{"custom_model_data":5372497},"model":"item/golden_carrot"},
{"predicate":{"custom_model_data":5372498},"model":"item/golden_helmet"},
{"predicate":{"custom_model_data":5372499},"model":"item/golden_shovel"},
{"predicate":{"custom_model_data":5372500},"model":"item/iron_leggings"},
{"predicate":{"custom_model_data":5372501},"model":"item/leather_boots"},
{"predicate":{"custom_model_data":5372502},"model":"item/mangrove_boat"},
{"predicate":{"custom_model_data":5372503},"model":"item/mushroom_stew"},
{"predicate":{"custom_model_data":5372504},"model":"item/music_disc_11"},
{"predicate":{"custom_model_data":5372505},"model":"item/music_disc_13"},
{"predicate":{"custom_model_data":5372506},"model":"item/netherite_axe"},
{"predicate":{"custom_model_data":5372507},"model":"item/netherite_hoe"},
{"predicate":{"custom_model_data":5372508},"model":"item/pig_spawn_egg"},
{"predicate":{"custom_model_data":5372509},"model":"item/pumpkin_seeds"},
{"predicate":{"custom_model_data":5372510},"model":"item/salmon_bucket"},
{"predicate":{"custom_model_data":5372511},"model":"item/blast_furnace"},
{"predicate":{"custom_model_data":5372512},"model":"item/blue_concrete"},
{"predicate":{"custom_model_data":5372513},"model":"item/brewing_stand"},
{"predicate":{"custom_model_data":5372514},"model":"item/cherry_button"},
{"predicate":{"custom_model_data":5372515},"model":"item/cherry_leaves"},
{"predicate":{"custom_model_data":5372516},"model":"item/cherry_planks"},
{"predicate":{"custom_model_data":5372517},"model":"item/cherry_stairs"},
{"predicate":{"custom_model_data":5372518},"model":"item/chipped_anvil"},
{"predicate":{"custom_model_data":5372519},"model":"item/chorus_flower"},
{"predicate":{"custom_model_data":5372520},"model":"item/command_block"},
{"predicate":{"custom_model_data":5372521},"model":"item/cow_spawn_egg"},
{"predicate":{"custom_model_data":5372522},"model":"item/crimson_fence"},
{"predicate":{"custom_model_data":5372523},"model":"item/crimson_roots"},
{"predicate":{"custom_model_data":5372524},"model":"item/cut_sandstone"},
{"predicate":{"custom_model_data":5372525},"model":"item/cyan_concrete"},
{"predicate":{"custom_model_data":5372526},"model":"item/damaged_anvil"},
{"predicate":{"custom_model_data":5372527},"model":"item/dark_oak_door"},
{"predicate":{"custom_model_data":5372528},"model":"item/dark_oak_sign"},
{"predicate":{"custom_model_data":5372529},"model":"item/dark_oak_slab"},
{"predicate":{"custom_model_data":5372530},"model":"item/dark_oak_wood"},
{"predicate":{"custom_model_data":5372531},"model":"item/decorated_pot"},
{"predicate":{"custom_model_data":5372532},"model":"item/detector_rail"},
{"predicate":{"custom_model_data":5372533},"model":"item/diamond_block"},
{"predicate":{"custom_model_data":5372534},"model":"item/diamond_boots"},
{"predicate":{"custom_model_data":5372535},"model":"item/diamond_sword"},
{"predicate":{"custom_model_data":5372536},"model":"item/emerald_block"},
{"predicate":{"custom_model_data":5372537},"model":"item/gray_concrete"},
{"predicate":{"custom_model_data":5372538},"model":"item/hanging_roots"},
{"predicate":{"custom_model_data":5372539},"model":"item/iron_trapdoor"},
{"predicate":{"custom_model_data":5372540},"model":"item/jungle_button"},
{"predicate":{"custom_model_data":5372541},"model":"item/jungle_leaves"},
{"predicate":{"custom_model_data":5372542},"model":"item/jungle_planks"},
{"predicate":{"custom_model_data":5372543},"model":"item/jungle_stairs"},
{"predicate":{"custom_model_data":5372544},"model":"item/lightning_rod"},
{"predicate":{"custom_model_data":5372545},"model":"item/lime_concrete"},
{"predicate":{"custom_model_data":5372546},"model":"item/mangrove_door"},
{"predicate":{"custom_model_data":5372547},"model":"item/mangrove_sign"},
{"predicate":{"custom_model_data":5372548},"model":"item/mangrove_slab"},
{"predicate":{"custom_model_data":5372549},"model":"item/mangrove_wood"},
{"predicate":{"custom_model_data":5372550},"model":"item/mushroom_stem"},
{"predicate":{"custom_model_data":5372551},"model":"item/nether_bricks"},
{"predicate":{"custom_model_data":5372552},"model":"item/orange_banner"},
{"predicate":{"custom_model_data":5372553},"model":"item/orange_candle"},
{"predicate":{"custom_model_data":5372554},"model":"item/orange_carpet"},
{"predicate":{"custom_model_data":5372555},"model":"item/pink_concrete"},
{"predicate":{"custom_model_data":5372556},"model":"item/pitcher_plant"},
{"predicate":{"custom_model_data":5372557},"model":"item/purple_banner"},
{"predicate":{"custom_model_data":5372558},"model":"item/purple_candle"},
{"predicate":{"custom_model_data":5372559},"model":"item/purple_carpet"},
{"predicate":{"custom_model_data":5372560},"model":"item/purpur_pillar"},
{"predicate":{"custom_model_data":5372561},"model":"item/purpur_stairs"},
{"predicate":{"custom_model_data":5372562},"model":"item/quartz_bricks"},
{"predicate":{"custom_model_data":5372563},"model":"item/quartz_pillar"},
{"predicate":{"custom_model_data":5372564},"model":"item/quartz_stairs"},
{"predicate":{"custom_model_data":5372565},"model":"item/red_sandstone"},
{"predicate":{"custom_model_data":5372566},"model":"item/redstone_lamp"},
{"predicate":{"custom_model_data":5372567},"model":"item/shulker_shell"},
{"predicate":{"custom_model_data":5372568},"model":"item/splash_potion"},
{"predicate":{"custom_model_data":5372569},"model":"item/stone_pickaxe"},
{"predicate":{"custom_model_data":5372570},"model":"item/tropical_fish"},
{"predicate":{"custom_model_data":5372571},"model":"item/turtle_helmet"},
{"predicate":{"custom_model_data":5372572},"model":"item/vex_spawn_egg"},
{"predicate":{"custom_model_data":5372573},"model":"item/wooden_shovel"},
{"predicate":{"custom_model_data":5372574},"model":"item/writable_book"},
{"predicate":{"custom_model_data":5372575},"model":"item/smooth_basalt"},
{"predicate":{"custom_model_data":5372576},"model":"item/smooth_quartz"},
{"predicate":{"custom_model_data":5372577},"model":"item/soul_campfire"},
{"predicate":{"custom_model_data":5372578},"model":"item/spore_blossom"},
{"predicate":{"custom_model_data":5372579},"model":"item/spruce_button"},
{"predicate":{"custom_model_data":5372580},"model":"item/spruce_leaves"},
{"predicate":{"custom_model_data":5372581},"model":"item/spruce_planks"},
{"predicate":{"custom_model_data":5372582},"model":"item/spruce_stairs"},
{"predicate":{"custom_model_data":5372583},"model":"item/sticky_piston"},
{"predicate":{"custom_model_data":5372584},"model":"item/sweet_berries"},
{"predicate":{"custom_model_data":5372585},"model":"item/trapped_chest"},
{"predicate":{"custom_model_data":5372586},"model":"item/tripwire_hook"},
{"predicate":{"custom_model_data":5372587},"model":"item/warped_button"},
{"predicate":{"custom_model_data":5372588},"model":"item/warped_fungus"},
{"predicate":{"custom_model_data":5372589},"model":"item/warped_hyphae"},
{"predicate":{"custom_model_data":5372590},"model":"item/warped_nylium"},
{"predicate":{"custom_model_data":5372591},"model":"item/warped_planks"},
{"predicate":{"custom_model_data":5372592},"model":"item/warped_stairs"},
{"predicate":{"custom_model_data":5372593},"model":"item/weeping_vines"},
{"predicate":{"custom_model_data":5372594},"model":"item/yellow_banner"},
{"predicate":{"custom_model_data":5372595},"model":"item/yellow_candle"},
{"predicate":{"custom_model_data":5372596},"model":"item/yellow_carpet"},
{"predicate":{"custom_model_data":5372597},"model":"item/amethyst_shard"},
{"predicate":{"custom_model_data":5372598},"model":"item/axolotl_bucket"},
{"predicate":{"custom_model_data":5372599},"model":"item/beetroot_seeds"},
{"predicate":{"custom_model_data":5372600},"model":"item/acacia_sapling"},
{"predicate":{"custom_model_data":5372601},"model":"item/activator_rail"},
{"predicate":{"custom_model_data":5372602},"model":"item/amethyst_block"},
{"predicate":{"custom_model_data":5372603},"model":"item/ancient_debris"},
{"predicate":{"custom_model_data":5372604},"model":"item/birch_trapdoor"},
{"predicate":{"custom_model_data":5372605},"model":"item/black_concrete"},
{"predicate":{"custom_model_data":5372606},"model":"item/chest_minecart"},
{"predicate":{"custom_model_data":5372607},"model":"item/cooked_chicken"},
{"predicate":{"custom_model_data":5372608},"model":"item/enchanted_book"},
{"predicate":{"custom_model_data":5372609},"model":"item/frog_spawn_egg"},
{"predicate":{"custom_model_data":5372610},"model":"item/glowstone_dust"},
{"predicate":{"custom_model_data":5372611},"model":"item/goat_spawn_egg"},
{"predicate":{"custom_model_data":5372612},"model":"item/golden_pickaxe"},
{"predicate":{"custom_model_data":5372613},"model":"item/husk_spawn_egg"},
{"predicate":{"custom_model_data":5372614},"model":"item/knowledge_book"},
{"predicate":{"custom_model_data":5372615},"model":"item/leather_helmet"},
{"predicate":{"custom_model_data":5372616},"model":"item/light_blue_dye"},
{"predicate":{"custom_model_data":5372617},"model":"item/light_gray_dye"},
{"predicate":{"custom_model_data":5372618},"model":"item/mule_spawn_egg"},
{"predicate":{"custom_model_data":5372619},"model":"item/music_disc_cat"},
{"predicate":{"custom_model_data":5372620},"model":"item/music_disc_far"},
{"predicate":{"custom_model_data":5372621},"model":"item/nautilus_shell"},
{"predicate":{"custom_model_data":5372622},"model":"item/oak_chest_boat"},
{"predicate":{"custom_model_data":5372623},"model":"item/brown_concrete"},
{"predicate":{"custom_model_data":5372624},"model":"item/brown_mushroom"},
{"predicate":{"custom_model_data":5372625},"model":"item/carved_pumpkin"},
{"predicate":{"custom_model_data":5372626},"model":"item/cherry_sapling"},
{"predicate":{"custom_model_data":5372627},"model":"item/crafting_table"},
{"predicate":{"custom_model_data":5372628},"model":"item/crimson_button"},
{"predicate":{"custom_model_data":5372629},"model":"item/crimson_fungus"},
{"predicate":{"custom_model_data":5372630},"model":"item/crimson_hyphae"},
{"predicate":{"custom_model_data":5372631},"model":"item/crimson_nylium"},
{"predicate":{"custom_model_data":5372632},"model":"item/crimson_planks"},
{"predicate":{"custom_model_data":5372633},"model":"item/crimson_stairs"},
{"predicate":{"custom_model_data":5372634},"model":"item/dark_oak_fence"},
{"predicate":{"custom_model_data":5372635},"model":"item/diamond_helmet"},
{"predicate":{"custom_model_data":5372636},"model":"item/diamond_shovel"},
{"predicate":{"custom_model_data":5372637},"model":"item/diorite_stairs"},
{"predicate":{"custom_model_data":5372638},"model":"item/exposed_copper"},
{"predicate":{"custom_model_data":5372639},"model":"item/fire_coral_fan"},
{"predicate":{"custom_model_data":5372640},"model":"item/granite_stairs"},
{"predicate":{"custom_model_data":5372641},"model":"item/green_concrete"},
{"predicate":{"custom_model_data":5372642},"model":"item/horn_coral_fan"},
{"predicate":{"custom_model_data":5372643},"model":"item/infested_stone"},
{"predicate":{"custom_model_data":5372644},"model":"item/jack_o_lantern"},
{"predicate":{"custom_model_data":5372645},"model":"item/jungle_sapling"},
{"predicate":{"custom_model_data":5372646},"model":"item/light_blue_bed"},
{"predicate":{"custom_model_data":5372647},"model":"item/light_gray_bed"},
{"predicate":{"custom_model_data":5372648},"model":"item/magenta_banner"},
{"predicate":{"custom_model_data":5372649},"model":"item/magenta_candle"},
{"predicate":{"custom_model_data":5372650},"model":"item/magenta_carpet"},
{"predicate":{"custom_model_data":5372651},"model":"item/mangrove_fence"},
{"predicate":{"custom_model_data":5372652},"model":"item/mangrove_roots"},
{"predicate":{"custom_model_data":5372653},"model":"item/mud_brick_slab"},
{"predicate":{"custom_model_data":5372654},"model":"item/mud_brick_wall"},
{"predicate":{"custom_model_data":5372655},"model":"item/nether_sprouts"},
{"predicate":{"custom_model_data":5372656},"model":"item/oak_fence_gate"},
{"predicate":{"custom_model_data":5372657},"model":"item/raw_gold_block"},
{"predicate":{"custom_model_data":5372658},"model":"item/raw_iron_block"},
{"predicate":{"custom_model_data":5372659},"model":"item/red_terracotta"},
{"predicate":{"custom_model_data":5372660},"model":"item/redstone_block"},
{"predicate":{"custom_model_data":5372661},"model":"item/redstone_torch"},
{"predicate":{"custom_model_data":5372662},"model":"item/respawn_anchor"},
{"predicate":{"custom_model_data":5372663},"model":"item/sandstone_slab"},
{"predicate":{"custom_model_data":5372664},"model":"item/sandstone_wall"},
{"predicate":{"custom_model_data":5372665},"model":"item/sculk_catalyst"},
{"predicate":{"custom_model_data":5372666},"model":"item/sculk_shrieker"},
{"predicate":{"custom_model_data":5372667},"model":"item/cod_spawn_egg"},
{"predicate":{"custom_model_data":5372668},"model":"item/spectral_arrow"},
{"predicate":{"custom_model_data":5372669},"model":"item/tadpole_bucket"},
{"predicate":{"custom_model_data":5372670},"model":"item/wolf_spawn_egg"},
{"predicate":{"custom_model_data":5372671},"model":"item/wooden_pickaxe"},
{"predicate":{"custom_model_data":5372672},"model":"item/skeleton_skull"},
{"predicate":{"custom_model_data":5372673},"model":"item/small_dripleaf"},
{"predicate":{"custom_model_data":5372674},"model":"item/smithing_table"},
{"predicate":{"custom_model_data":5372675},"model":"item/spruce_sapling"},
{"predicate":{"custom_model_data":5372676},"model":"item/structure_void"},
{"predicate":{"custom_model_data":5372677},"model":"item/tube_coral_fan"},
{"predicate":{"custom_model_data":5372678},"model":"item/twisting_vines"},
{"predicate":{"custom_model_data":5372679},"model":"item/white_concrete"},
{"predicate":{"custom_model_data":5372680},"model":"item/allay_spawn_egg"},
{"predicate":{"custom_model_data":5372681},"model":"item/acacia_trapdoor"},
{"predicate":{"custom_model_data":5372682},"model":"item/andesite_stairs"},
{"predicate":{"custom_model_data":5372683},"model":"item/bamboo_trapdoor"},
{"predicate":{"custom_model_data":5372684},"model":"item/blaze_spawn_egg"},
{"predicate":{"custom_model_data":5372685},"model":"item/chainmail_boots"},
{"predicate":{"custom_model_data":5372686},"model":"item/cooked_porkchop"},
{"predicate":{"custom_model_data":5372687},"model":"item/disc_fragment_5"},
{"predicate":{"custom_model_data":5372688},"model":"item/firework_rocket"},
{"predicate":{"custom_model_data":5372689},"model":"item/flint_and_steel"},
{"predicate":{"custom_model_data":5372690},"model":"item/ghast_spawn_egg"},
{"predicate":{"custom_model_data":5372691},"model":"item/glow_item_frame"},
{"predicate":{"custom_model_data":5372692},"model":"item/golden_leggings"},
{"predicate":{"custom_model_data":5372693},"model":"item/hopper_minecart"},
{"predicate":{"custom_model_data":5372694},"model":"item/horse_spawn_egg"},
{"predicate":{"custom_model_data":5372695},"model":"item/iron_chestplate"},
{"predicate":{"custom_model_data":5372696},"model":"item/llama_spawn_egg"},
{"predicate":{"custom_model_data":5372697},"model":"item/music_disc_mall"},
{"predicate":{"custom_model_data":5372698},"model":"item/music_disc_stal"},
{"predicate":{"custom_model_data":5372699},"model":"item/music_disc_wait"},
{"predicate":{"custom_model_data":5372700},"model":"item/music_disc_ward"},
{"predicate":{"custom_model_data":5372701},"model":"item/netherite_block"},
{"predicate":{"custom_model_data":5372702},"model":"item/netherite_boots"},
{"predicate":{"custom_model_data":5372703},"model":"item/netherite_ingot"},
{"predicate":{"custom_model_data":5372704},"model":"item/netherite_scrap"},
{"predicate":{"custom_model_data":5372705},"model":"item/netherite_sword"},
{"predicate":{"custom_model_data":5372706},"model":"item/panda_spawn_egg"},
{"predicate":{"custom_model_data":5372707},"model":"item/blackstone_slab"},
{"predicate":{"custom_model_data":5372708},"model":"item/blackstone_wall"},
{"predicate":{"custom_model_data":5372709},"model":"item/blue_terracotta"},
{"predicate":{"custom_model_data":5372710},"model":"item/brain_coral_fan"},
{"predicate":{"custom_model_data":5372711},"model":"item/camel_spawn_egg"},
{"predicate":{"custom_model_data":5372712},"model":"item/cherry_trapdoor"},
{"predicate":{"custom_model_data":5372713},"model":"item/crying_obsidian"},
{"predicate":{"custom_model_data":5372714},"model":"item/cut_copper_slab"},
{"predicate":{"custom_model_data":5372715},"model":"item/cyan_terracotta"},
{"predicate":{"custom_model_data":5372716},"model":"item/dark_oak_button"},
{"predicate":{"custom_model_data":5372717},"model":"item/dark_oak_leaves"},
{"predicate":{"custom_model_data":5372718},"model":"item/dark_oak_planks"},
{"predicate":{"custom_model_data":5372719},"model":"item/dark_oak_stairs"},
{"predicate":{"custom_model_data":5372720},"model":"item/dark_prismarine"},
{"predicate":{"custom_model_data":5372721},"model":"item/dead_fire_coral"},
{"predicate":{"custom_model_data":5372722},"model":"item/dead_horn_coral"},
{"predicate":{"custom_model_data":5372723},"model":"item/dead_tube_coral"},
{"predicate":{"custom_model_data":5372724},"model":"item/deepslate_tiles"},
{"predicate":{"custom_model_data":5372725},"model":"item/diamond_pickaxe"},
{"predicate":{"custom_model_data":5372726},"model":"item/dripstone_block"},
{"predicate":{"custom_model_data":5372727},"model":"item/fletching_table"},
{"predicate":{"custom_model_data":5372728},"model":"item/gray_terracotta"},
{"predicate":{"custom_model_data":5372729},"model":"item/honeycomb_block"},
{"predicate":{"custom_model_data":5372730},"model":"item/jungle_trapdoor"},
{"predicate":{"custom_model_data":5372731},"model":"item/light_blue_wool"},
{"predicate":{"custom_model_data":5372732},"model":"item/light_gray_wool"},
{"predicate":{"custom_model_data":5372733},"model":"item/lime_terracotta"},
{"predicate":{"custom_model_data":5372734},"model":"item/mangrove_button"},
{"predicate":{"custom_model_data":5372735},"model":"item/mangrove_leaves"},
{"predicate":{"custom_model_data":5372736},"model":"item/mangrove_planks"},
{"predicate":{"custom_model_data":5372737},"model":"item/mangrove_stairs"},
{"predicate":{"custom_model_data":5372738},"model":"item/nether_gold_ore"},
{"predicate":{"custom_model_data":5372739},"model":"item/ochre_froglight"},
{"predicate":{"custom_model_data":5372740},"model":"item/orange_concrete"},
{"predicate":{"custom_model_data":5372741},"model":"item/oxidized_copper"},
{"predicate":{"custom_model_data":5372742},"model":"item/pink_terracotta"},
{"predicate":{"custom_model_data":5372743},"model":"item/polished_basalt"},
{"predicate":{"custom_model_data":5372744},"model":"item/prismarine_slab"},
{"predicate":{"custom_model_data":5372745},"model":"item/prismarine_wall"},
{"predicate":{"custom_model_data":5372746},"model":"item/purple_concrete"},
{"predicate":{"custom_model_data":5372747},"model":"item/red_shulker_box"},
{"predicate":{"custom_model_data":5372748},"model":"item/sheep_spawn_egg"},
{"predicate":{"custom_model_data":5372749},"model":"item/slime_spawn_egg"},
{"predicate":{"custom_model_data":5372750},"model":"item/squid_spawn_egg"},
{"predicate":{"custom_model_data":5372751},"model":"item/stray_spawn_egg"},
{"predicate":{"custom_model_data":5372752},"model":"item/suspicious_stew"},
{"predicate":{"custom_model_data":5372753},"model":"item/witch_spawn_egg"},
{"predicate":{"custom_model_data":5372754},"model":"item/spruce_trapdoor"},
{"predicate":{"custom_model_data":5372755},"model":"item/structure_block"},
{"predicate":{"custom_model_data":5372756},"model":"item/suspicious_sand"},
{"predicate":{"custom_model_data":5372757},"model":"item/warped_trapdoor"},
{"predicate":{"custom_model_data":5372758},"model":"item/yellow_concrete"},
{"predicate":{"custom_model_data":5372759},"model":"item/birch_chest_boat"},
{"predicate":{"custom_model_data":5372760},"model":"item/amethyst_cluster"},
{"predicate":{"custom_model_data":5372761},"model":"item/birch_fence_gate"},
{"predicate":{"custom_model_data":5372762},"model":"item/chainmail_helmet"},
{"predicate":{"custom_model_data":5372763},"model":"item/donkey_spawn_egg"},
{"predicate":{"custom_model_data":5372764},"model":"item/evoker_spawn_egg"},
{"predicate":{"custom_model_data":5372765},"model":"item/furnace_minecart"},
{"predicate":{"custom_model_data":5372766},"model":"item/heart_of_the_sea"},
{"predicate":{"custom_model_data":5372767},"model":"item/hoglin_spawn_egg"},
{"predicate":{"custom_model_data":5372768},"model":"item/iron_horse_armor"},
{"predicate":{"custom_model_data":5372769},"model":"item/leather_leggings"},
{"predicate":{"custom_model_data":5372770},"model":"item/lingering_potion"},
{"predicate":{"custom_model_data":5372771},"model":"item/music_disc_chirp"},
{"predicate":{"custom_model_data":5372772},"model":"item/music_disc_relic"},
{"predicate":{"custom_model_data":5372773},"model":"item/music_disc_strad"},
{"predicate":{"custom_model_data":5372774},"model":"item/netherite_helmet"},
{"predicate":{"custom_model_data":5372775},"model":"item/netherite_shovel"},
{"predicate":{"custom_model_data":5372776},"model":"item/ocelot_spawn_egg"},
{"predicate":{"custom_model_data":5372777},"model":"item/parrot_spawn_egg"},
{"predicate":{"custom_model_data":5372778},"model":"item/phantom_membrane"},
{"predicate":{"custom_model_data":5372779},"model":"item/piglin_spawn_egg"},
{"predicate":{"custom_model_data":5372780},"model":"item/poisonous_potato"},
{"predicate":{"custom_model_data":5372781},"model":"item/rabbit_spawn_egg"},
{"predicate":{"custom_model_data":5372782},"model":"item/salmon_spawn_egg"},
{"predicate":{"custom_model_data":5372783},"model":"item/black_terracotta"},
{"predicate":{"custom_model_data":5372784},"model":"item/blue_shulker_box"},
{"predicate":{"custom_model_data":5372785},"model":"item/brown_terracotta"},
{"predicate":{"custom_model_data":5372786},"model":"item/bubble_coral_fan"},
{"predicate":{"custom_model_data":5372787},"model":"item/budding_amethyst"},
{"predicate":{"custom_model_data":5372788},"model":"item/cobblestone_slab"},
{"predicate":{"custom_model_data":5372789},"model":"item/cobblestone_wall"},
{"predicate":{"custom_model_data":5372790},"model":"item/crimson_trapdoor"},
{"predicate":{"custom_model_data":5372791},"model":"item/cyan_shulker_box"},
{"predicate":{"custom_model_data":5372792},"model":"item/dark_oak_sapling"},
{"predicate":{"custom_model_data":5372793},"model":"item/dead_brain_coral"},
{"predicate":{"custom_model_data":5372794},"model":"item/deepslate_bricks"},
{"predicate":{"custom_model_data":5372795},"model":"item/diamond_leggings"},
{"predicate":{"custom_model_data":5372796},"model":"item/dried_kelp_block"},
{"predicate":{"custom_model_data":5372797},"model":"item/enchanting_table"},
{"predicate":{"custom_model_data":5372798},"model":"item/end_portal_frame"},
{"predicate":{"custom_model_data":5372799},"model":"item/end_stone_bricks"},
{"predicate":{"custom_model_data":5372800},"model":"item/fire_coral_block"},
{"predicate":{"custom_model_data":5372801},"model":"item/flowering_azalea"},
{"predicate":{"custom_model_data":5372802},"model":"item/gray_shulker_box"},
{"predicate":{"custom_model_data":5372803},"model":"item/green_terracotta"},
{"predicate":{"custom_model_data":5372804},"model":"item/horn_coral_block"},
{"predicate":{"custom_model_data":5372805},"model":"item/lime_shulker_box"},
{"predicate":{"custom_model_data":5372806},"model":"item/magenta_concrete"},
{"predicate":{"custom_model_data":5372807},"model":"item/mud_brick_stairs"},
{"predicate":{"custom_model_data":5372808},"model":"item/oak_hanging_sign"},
{"predicate":{"custom_model_data":5372809},"model":"item/pink_shulker_box"},
{"predicate":{"custom_model_data":5372810},"model":"item/polished_diorite"},
{"predicate":{"custom_model_data":5372811},"model":"item/polished_granite"},
{"predicate":{"custom_model_data":5372812},"model":"item/prismarine_shard"},
{"predicate":{"custom_model_data":5372813},"model":"item/raw_copper_block"},
{"predicate":{"custom_model_data":5372814},"model":"item/recovery_compass"},
{"predicate":{"custom_model_data":5372815},"model":"item/sandstone_stairs"},
{"predicate":{"custom_model_data":5372816},"model":"item/spider_spawn_egg"},
{"predicate":{"custom_model_data":5372817},"model":"item/totem_of_undying"},
{"predicate":{"custom_model_data":5372818},"model":"item/warden_spawn_egg"},
{"predicate":{"custom_model_data":5372819},"model":"item/wither_spawn_egg"},
{"predicate":{"custom_model_data":5372820},"model":"item/zoglin_spawn_egg"},
{"predicate":{"custom_model_data":5372821},"model":"item/smooth_sandstone"},
{"predicate":{"custom_model_data":5372822},"model":"item/stone_brick_slab"},
{"predicate":{"custom_model_data":5372823},"model":"item/stone_brick_wall"},
{"predicate":{"custom_model_data":5372824},"model":"item/stripped_oak_log"},
{"predicate":{"custom_model_data":5372825},"model":"item/tube_coral_block"},
{"predicate":{"custom_model_data":5372826},"model":"item/turtle_spawn_egg"},
{"predicate":{"custom_model_data":5372827},"model":"item/waxed_cut_copper"},
{"predicate":{"custom_model_data":5372828},"model":"item/weathered_copper"},
{"predicate":{"custom_model_data":5372829},"model":"item/white_terracotta"},
{"predicate":{"custom_model_data":5372830},"model":"item/acacia_chest_boat"},
{"predicate":{"custom_model_data":5372831},"model":"item/acacia_fence_gate"},
{"predicate":{"custom_model_data":5372832},"model":"item/axolotl_spawn_egg"},
{"predicate":{"custom_model_data":5372833},"model":"item/bamboo_chest_raft"},
{"predicate":{"custom_model_data":5372834},"model":"item/bamboo_fence_gate"},
{"predicate":{"custom_model_data":5372835},"model":"item/carrot_on_a_stick"},
{"predicate":{"custom_model_data":5372836},"model":"item/cherry_chest_boat"},
{"predicate":{"custom_model_data":5372837},"model":"item/chicken_spawn_egg"},
{"predicate":{"custom_model_data":5372838},"model":"item/creeper_spawn_egg"},
{"predicate":{"custom_model_data":5372839},"model":"item/dolphin_spawn_egg"},
{"predicate":{"custom_model_data":5372840},"model":"item/drowned_spawn_egg"},
{"predicate":{"custom_model_data":5372841},"model":"item/experience_bottle"},
{"predicate":{"custom_model_data":5372842},"model":"item/golden_chestplate"},
{"predicate":{"custom_model_data":5372843},"model":"item/jungle_chest_boat"},
{"predicate":{"custom_model_data":5372844},"model":"item/music_disc_blocks"},
{"predicate":{"custom_model_data":5372845},"model":"item/netherite_pickaxe"},
{"predicate":{"custom_model_data":5372846},"model":"item/phantom_spawn_egg"},
{"predicate":{"custom_model_data":5372847},"model":"item/pufferfish_bucket"},
{"predicate":{"custom_model_data":5372848},"model":"item/ravager_spawn_egg"},
{"predicate":{"custom_model_data":5372849},"model":"item/black_shulker_box"},
{"predicate":{"custom_model_data":5372850},"model":"item/blackstone_stairs"},
{"predicate":{"custom_model_data":5372851},"model":"item/brain_coral_block"},
{"predicate":{"custom_model_data":5372852},"model":"item/brown_shulker_box"},
{"predicate":{"custom_model_data":5372853},"model":"item/cartography_table"},
{"predicate":{"custom_model_data":5372854},"model":"item/cherry_fence_gate"},
{"predicate":{"custom_model_data":5372855},"model":"item/cobbled_deepslate"},
{"predicate":{"custom_model_data":5372856},"model":"item/cut_copper_stairs"},
{"predicate":{"custom_model_data":5372857},"model":"item/cut_red_sandstone"},
{"predicate":{"custom_model_data":5372858},"model":"item/dark_oak_trapdoor"},
{"predicate":{"custom_model_data":5372859},"model":"item/daylight_detector"},
{"predicate":{"custom_model_data":5372860},"model":"item/dead_bubble_coral"},
{"predicate":{"custom_model_data":5372861},"model":"item/gilded_blackstone"},
{"predicate":{"custom_model_data":5372862},"model":"item/green_shulker_box"},
{"predicate":{"custom_model_data":5372863},"model":"item/jungle_fence_gate"},
{"predicate":{"custom_model_data":5372864},"model":"item/light_blue_banner"},
{"predicate":{"custom_model_data":5372865},"model":"item/light_blue_candle"},
{"predicate":{"custom_model_data":5372866},"model":"item/light_blue_carpet"},
{"predicate":{"custom_model_data":5372867},"model":"item/light_gray_banner"},
{"predicate":{"custom_model_data":5372868},"model":"item/light_gray_candle"},
{"predicate":{"custom_model_data":5372869},"model":"item/light_gray_carpet"},
{"predicate":{"custom_model_data":5372870},"model":"item/mangrove_trapdoor"},
{"predicate":{"custom_model_data":5372871},"model":"item/mossy_cobblestone"},
{"predicate":{"custom_model_data":5372872},"model":"item/nether_brick_slab"},
{"predicate":{"custom_model_data":5372873},"model":"item/nether_brick_wall"},
{"predicate":{"custom_model_data":5372874},"model":"item/nether_quartz_ore"},
{"predicate":{"custom_model_data":5372875},"model":"item/nether_wart_block"},
{"predicate":{"custom_model_data":5372876},"model":"item/orange_terracotta"},
{"predicate":{"custom_model_data":5372877},"model":"item/pointed_dripstone"},
{"predicate":{"custom_model_data":5372878},"model":"item/polished_andesite"},
{"predicate":{"custom_model_data":5372879},"model":"item/prismarine_bricks"},
{"predicate":{"custom_model_data":5372880},"model":"item/prismarine_stairs"},
{"predicate":{"custom_model_data":5372881},"model":"item/purple_terracotta"},
{"predicate":{"custom_model_data":5372882},"model":"item/red_nether_bricks"},
{"predicate":{"custom_model_data":5372883},"model":"item/red_stained_glass"},
{"predicate":{"custom_model_data":5372884},"model":"item/zombie_spawn_egg"},
{"predicate":{"custom_model_data":5372885},"model":"item/shulker_spawn_egg"},
{"predicate":{"custom_model_data":5372886},"model":"item/sniffer_spawn_egg"},
{"predicate":{"custom_model_data":5372887},"model":"item/spruce_chest_boat"},
{"predicate":{"custom_model_data":5372888},"model":"item/strider_spawn_egg"},
{"predicate":{"custom_model_data":5372889},"model":"item/tadpole_spawn_egg"},
{"predicate":{"custom_model_data":5372890},"model":"item/smooth_stone_slab"},
{"predicate":{"custom_model_data":5372891},"model":"item/spruce_fence_gate"},
{"predicate":{"custom_model_data":5372892},"model":"item/stripped_oak_wood"},
{"predicate":{"custom_model_data":5372893},"model":"item/suspicious_gravel"},
{"predicate":{"custom_model_data":5372894},"model":"item/torchflower_seeds"},
{"predicate":{"custom_model_data":5372895},"model":"item/verdant_froglight"},
{"predicate":{"custom_model_data":5372896},"model":"item/warped_fence_gate"},
{"predicate":{"custom_model_data":5372897},"model":"item/warped_wart_block"},
{"predicate":{"custom_model_data":5372898},"model":"item/white_shulker_box"},
{"predicate":{"custom_model_data":5372899},"model":"item/yellow_terracotta"},
{"predicate":{"custom_model_data":5372900},"model":"item/bamboo_mosaic_slab"},
{"predicate":{"custom_model_data":5372901},"model":"item/birch_hanging_sign"},
{"predicate":{"custom_model_data":5372902},"model":"item/chainmail_leggings"},
{"predicate":{"custom_model_data":5372903},"model":"item/enderman_spawn_egg"},
{"predicate":{"custom_model_data":5372904},"model":"item/golden_horse_armor"},
{"predicate":{"custom_model_data":5372905},"model":"item/guardian_spawn_egg"},
{"predicate":{"custom_model_data":5372906},"model":"item/howl_pottery_sherd"},
{"predicate":{"custom_model_data":5372907},"model":"item/leather_chestplate"},
{"predicate":{"custom_model_data":5372908},"model":"item/music_disc_mellohi"},
{"predicate":{"custom_model_data":5372909},"model":"item/music_disc_pigstep"},
{"predicate":{"custom_model_data":5372910},"model":"item/netherite_leggings"},
{"predicate":{"custom_model_data":5372911},"model":"item/pillager_spawn_egg"},
{"predicate":{"custom_model_data":5372912},"model":"item/blue_stained_glass"},
{"predicate":{"custom_model_data":5372913},"model":"item/bubble_coral_block"},
{"predicate":{"custom_model_data":5372914},"model":"item/burn_pottery_sherd"},
{"predicate":{"custom_model_data":5372915},"model":"item/chiseled_bookshelf"},
{"predicate":{"custom_model_data":5372916},"model":"item/chiseled_deepslate"},
{"predicate":{"custom_model_data":5372917},"model":"item/chiseled_sandstone"},
{"predicate":{"custom_model_data":5372918},"model":"item/cobblestone_stairs"},
{"predicate":{"custom_model_data":5372919},"model":"item/crimson_fence_gate"},
{"predicate":{"custom_model_data":5372920},"model":"item/cut_sandstone_slab"},
{"predicate":{"custom_model_data":5372921},"model":"item/cyan_stained_glass"},
{"predicate":{"custom_model_data":5372922},"model":"item/deepslate_coal_ore"},
{"predicate":{"custom_model_data":5372923},"model":"item/deepslate_gold_ore"},
{"predicate":{"custom_model_data":5372924},"model":"item/deepslate_iron_ore"},
{"predicate":{"custom_model_data":5372925},"model":"item/diamond_chestplate"},
{"predicate":{"custom_model_data":5372926},"model":"item/exposed_cut_copper"},
{"predicate":{"custom_model_data":5372927},"model":"item/gray_stained_glass"},
{"predicate":{"custom_model_data":5372928},"model":"item/infested_deepslate"},
{"predicate":{"custom_model_data":5372929},"model":"item/large_amethyst_bud"},
{"predicate":{"custom_model_data":5372930},"model":"item/lily_of_the_valley"},
{"predicate":{"custom_model_data":5372931},"model":"item/lime_stained_glass"},
{"predicate":{"custom_model_data":5372932},"model":"item/magenta_terracotta"},
{"predicate":{"custom_model_data":5372933},"model":"item/mangrove_propagule"},
{"predicate":{"custom_model_data":5372934},"model":"item/mossy_stone_bricks"},
{"predicate":{"custom_model_data":5372935},"model":"item/nether_brick_fence"},
{"predicate":{"custom_model_data":5372936},"model":"item/oak_pressure_plate"},
{"predicate":{"custom_model_data":5372937},"model":"item/orange_shulker_box"},
{"predicate":{"custom_model_data":5372938},"model":"item/petrified_oak_slab"},
{"predicate":{"custom_model_data":5372939},"model":"item/pink_stained_glass"},
{"predicate":{"custom_model_data":5372940},"model":"item/polished_deepslate"},
{"predicate":{"custom_model_data":5372941},"model":"item/powder_snow_bucket"},
{"predicate":{"custom_model_data":5372942},"model":"item/purple_shulker_box"},
{"predicate":{"custom_model_data":5372943},"model":"item/red_mushroom_block"},
{"predicate":{"custom_model_data":5372944},"model":"item/red_sandstone_slab"},
{"predicate":{"custom_model_data":5372945},"model":"item/red_sandstone_wall"},
{"predicate":{"custom_model_data":5372946},"model":"item/skeleton_spawn_egg"},
{"predicate":{"custom_model_data":5372947},"model":"item/villager_spawn_egg"},
{"predicate":{"custom_model_data":5372948},"model":"item/small_amethyst_bud"},
{"predicate":{"custom_model_data":5372949},"model":"item/smooth_quartz_slab"},
{"predicate":{"custom_model_data":5372950},"model":"item/stone_brick_stairs"},
{"predicate":{"custom_model_data":5372951},"model":"item/stripped_birch_log"},
{"predicate":{"custom_model_data":5372952},"model":"item/waxed_copper_block"},
{"predicate":{"custom_model_data":5372953},"model":"item/yellow_shulker_box"},
{"predicate":{"custom_model_data":5372954},"model":"item/acacia_hanging_sign"},
{"predicate":{"custom_model_data":5372955},"model":"item/bamboo_hanging_sign"},
{"predicate":{"custom_model_data":5372956},"model":"item/dark_oak_chest_boat"},
{"predicate":{"custom_model_data":5372957},"model":"item/endermite_spawn_egg"},
{"predicate":{"custom_model_data":5372958},"model":"item/heart_pottery_sherd"},
{"predicate":{"custom_model_data":5372959},"model":"item/leather_horse_armor"},
{"predicate":{"custom_model_data":5372960},"model":"item/mangrove_chest_boat"},
{"predicate":{"custom_model_data":5372961},"model":"item/miner_pottery_sherd"},
{"predicate":{"custom_model_data":5372962},"model":"item/mooshroom_spawn_egg"},
{"predicate":{"custom_model_data":5372963},"model":"item/prize_pottery_sherd"},
{"predicate":{"custom_model_data":5372964},"model":"item/black_stained_glass"},
{"predicate":{"custom_model_data":5372965},"model":"item/blade_pottery_sherd"},
{"predicate":{"custom_model_data":5372966},"model":"item/brown_stained_glass"},
{"predicate":{"custom_model_data":5372967},"model":"item/chain_command_block"},
{"predicate":{"custom_model_data":5372968},"model":"item/cherry_hanging_sign"},
{"predicate":{"custom_model_data":5372969},"model":"item/dark_oak_fence_gate"},
{"predicate":{"custom_model_data":5372970},"model":"item/dead_fire_coral_fan"},
{"predicate":{"custom_model_data":5372971},"model":"item/dead_horn_coral_fan"},
{"predicate":{"custom_model_data":5372972},"model":"item/dead_tube_coral_fan"},
{"predicate":{"custom_model_data":5372973},"model":"item/deepslate_lapis_ore"},
{"predicate":{"custom_model_data":5372974},"model":"item/deepslate_tile_slab"},
{"predicate":{"custom_model_data":5372975},"model":"item/deepslate_tile_wall"},
{"predicate":{"custom_model_data":5372976},"model":"item/diamond_horse_armor"},
{"predicate":{"custom_model_data":5372977},"model":"item/green_stained_glass"},
{"predicate":{"custom_model_data":5372978},"model":"item/jungle_hanging_sign"},
{"predicate":{"custom_model_data":5372979},"model":"item/light_blue_concrete"},
{"predicate":{"custom_model_data":5372980},"model":"item/light_gray_concrete"},
{"predicate":{"custom_model_data":5372981},"model":"item/magenta_shulker_box"},
{"predicate":{"custom_model_data":5372982},"model":"item/mangrove_fence_gate"},
{"predicate":{"custom_model_data":5372983},"model":"item/medium_amethyst_bud"},
{"predicate":{"custom_model_data":5372984},"model":"item/nether_brick_stairs"},
{"predicate":{"custom_model_data":5372985},"model":"item/oxidized_cut_copper"},
{"predicate":{"custom_model_data":5372986},"model":"item/polished_blackstone"},
{"predicate":{"custom_model_data":5372987},"model":"item/popped_chorus_fruit"},
{"predicate":{"custom_model_data":5372988},"model":"item/prismarine_crystals"},
{"predicate":{"custom_model_data":5372989},"model":"item/red_concrete_powder"},
{"predicate":{"custom_model_data":5372990},"model":"item/sheaf_pottery_sherd"},
{"predicate":{"custom_model_data":5372991},"model":"item/skull_pottery_sherd"},
{"predicate":{"custom_model_data":5372992},"model":"item/snort_pottery_sherd"},
{"predicate":{"custom_model_data":5372993},"model":"item/spruce_hanging_sign"},
{"predicate":{"custom_model_data":5372994},"model":"item/stripped_acacia_log"},
{"predicate":{"custom_model_data":5372995},"model":"item/stripped_birch_wood"},
{"predicate":{"custom_model_data":5372996},"model":"item/stripped_cherry_log"},
{"predicate":{"custom_model_data":5372997},"model":"item/stripped_jungle_log"},
{"predicate":{"custom_model_data":5372998},"model":"item/stripped_spruce_log"},
{"predicate":{"custom_model_data":5372999},"model":"item/warped_hanging_sign"},
{"predicate":{"custom_model_data":53721000},"model":"item/white_stained_glass"},
{"predicate":{"custom_model_data":53721001},"model":"item/angler_pottery_sherd"},
{"predicate":{"custom_model_data":53721002},"model":"item/archer_pottery_sherd"},
{"predicate":{"custom_model_data":53721003},"model":"item/bamboo_mosaic_stairs"},
{"predicate":{"custom_model_data":53721004},"model":"item/birch_pressure_plate"},
{"predicate":{"custom_model_data":53721005},"model":"item/chainmail_chestplate"},
{"predicate":{"custom_model_data":53721006},"model":"item/danger_pottery_sherd"},
{"predicate":{"custom_model_data":53721007},"model":"item/fermented_spider_eye"},
{"predicate":{"custom_model_data":53721008},"model":"item/friend_pottery_sherd"},
{"predicate":{"custom_model_data":53721009},"model":"item/globe_banner_pattern"},
{"predicate":{"custom_model_data":53721010},"model":"item/glow_squid_spawn_egg"},
{"predicate":{"custom_model_data":53721011},"model":"item/iron_golem_spawn_egg"},
{"predicate":{"custom_model_data":53721012},"model":"item/music_disc_otherside"},
{"predicate":{"custom_model_data":53721013},"model":"item/netherite_chestplate"},
{"predicate":{"custom_model_data":53721014},"model":"item/pufferfish_spawn_egg"},
{"predicate":{"custom_model_data":53721015},"model":"item/blue_concrete_powder"},
{"predicate":{"custom_model_data":53721016},"model":"item/brewer_pottery_sherd"},
{"predicate":{"custom_model_data":53721017},"model":"item/brown_mushroom_block"},
{"predicate":{"custom_model_data":53721018},"model":"item/cracked_stone_bricks"},
{"predicate":{"custom_model_data":53721019},"model":"item/crimson_hanging_sign"},
{"predicate":{"custom_model_data":53721020},"model":"item/cyan_concrete_powder"},
{"predicate":{"custom_model_data":53721021},"model":"item/dark_prismarine_slab"},
{"predicate":{"custom_model_data":53721022},"model":"item/dead_brain_coral_fan"},
{"predicate":{"custom_model_data":53721023},"model":"item/deepslate_brick_slab"},
{"predicate":{"custom_model_data":53721024},"model":"item/deepslate_brick_wall"},
{"predicate":{"custom_model_data":53721025},"model":"item/deepslate_copper_ore"},
{"predicate":{"custom_model_data":53721026},"model":"item/end_stone_brick_slab"},
{"predicate":{"custom_model_data":53721027},"model":"item/end_stone_brick_wall"},
{"predicate":{"custom_model_data":53721028},"model":"item/gray_concrete_powder"},
{"predicate":{"custom_model_data":53721029},"model":"item/infested_cobblestone"},
{"predicate":{"custom_model_data":53721030},"model":"item/lime_concrete_powder"},
{"predicate":{"custom_model_data":53721031},"model":"item/magma_cube_spawn_egg"},
{"predicate":{"custom_model_data":53721032},"model":"item/muddy_mangrove_roots"},
{"predicate":{"custom_model_data":53721033},"model":"item/orange_stained_glass"},
{"predicate":{"custom_model_data":53721034},"model":"item/pink_concrete_powder"},
{"predicate":{"custom_model_data":53721035},"model":"item/plenty_pottery_sherd"},
{"predicate":{"custom_model_data":53721036},"model":"item/polar_bear_spawn_egg"},
{"predicate":{"custom_model_data":53721037},"model":"item/purple_stained_glass"},
{"predicate":{"custom_model_data":53721038},"model":"item/red_sandstone_stairs"},
{"predicate":{"custom_model_data":53721039},"model":"item/reinforced_deepslate"},
{"predicate":{"custom_model_data":53721040},"model":"item/silverfish_spawn_egg"},
{"predicate":{"custom_model_data":53721041},"model":"item/skull_banner_pattern"},
{"predicate":{"custom_model_data":53721042},"model":"item/snow_golem_spawn_egg"},
{"predicate":{"custom_model_data":53721043},"model":"item/tropical_fish_bucket"},
{"predicate":{"custom_model_data":53721044},"model":"item/vindicator_spawn_egg"},
{"predicate":{"custom_model_data":53721045},"model":"item/smooth_quartz_stairs"},
{"predicate":{"custom_model_data":53721046},"model":"item/smooth_red_sandstone"},
{"predicate":{"custom_model_data":53721047},"model":"item/stone_pressure_plate"},
{"predicate":{"custom_model_data":53721048},"model":"item/stripped_acacia_wood"},
{"predicate":{"custom_model_data":53721049},"model":"item/stripped_cherry_wood"},
{"predicate":{"custom_model_data":53721050},"model":"item/stripped_jungle_wood"},
{"predicate":{"custom_model_data":53721051},"model":"item/stripped_spruce_wood"},
{"predicate":{"custom_model_data":53721052},"model":"item/stripped_warped_stem"},
{"predicate":{"custom_model_data":53721053},"model":"item/waxed_exposed_copper"},
{"predicate":{"custom_model_data":53721054},"model":"item/weathered_cut_copper"},
{"predicate":{"custom_model_data":53721055},"model":"item/yellow_stained_glass"},
{"predicate":{"custom_model_data":53721056},"model":"item/arms_up_pottery_sherd"},
{"predicate":{"custom_model_data":53721057},"model":"item/acacia_pressure_plate"},
{"predicate":{"custom_model_data":53721058},"model":"item/bamboo_pressure_plate"},
{"predicate":{"custom_model_data":53721059},"model":"item/black_concrete_powder"},
{"predicate":{"custom_model_data":53721060},"model":"item/cave_spider_spawn_egg"},
{"predicate":{"custom_model_data":53721061},"model":"item/mojang_banner_pattern"},
{"predicate":{"custom_model_data":53721062},"model":"item/mourner_pottery_sherd"},
{"predicate":{"custom_model_data":53721063},"model":"item/piglin_banner_pattern"},
{"predicate":{"custom_model_data":53721064},"model":"item/brown_concrete_powder"},
{"predicate":{"custom_model_data":53721065},"model":"item/cherry_pressure_plate"},
{"predicate":{"custom_model_data":53721066},"model":"item/chiseled_quartz_block"},
{"predicate":{"custom_model_data":53721067},"model":"item/chiseled_stone_bricks"},
{"predicate":{"custom_model_data":53721068},"model":"item/cracked_nether_bricks"},
{"predicate":{"custom_model_data":53721069},"model":"item/dark_oak_hanging_sign"},
{"predicate":{"custom_model_data":53721070},"model":"item/dead_bubble_coral_fan"},
{"predicate":{"custom_model_data":53721071},"model":"item/dead_fire_coral_block"},
{"predicate":{"custom_model_data":53721072},"model":"item/dead_horn_coral_block"},
{"predicate":{"custom_model_data":53721073},"model":"item/dead_tube_coral_block"},
{"predicate":{"custom_model_data":53721074},"model":"item/deepslate_diamond_ore"},
{"predicate":{"custom_model_data":53721075},"model":"item/deepslate_emerald_ore"},
{"predicate":{"custom_model_data":53721076},"model":"item/deepslate_tile_stairs"},
{"predicate":{"custom_model_data":53721077},"model":"item/flower_banner_pattern"},
{"predicate":{"custom_model_data":53721078},"model":"item/green_concrete_powder"},
{"predicate":{"custom_model_data":53721079},"model":"item/infested_stone_bricks"},
{"predicate":{"custom_model_data":53721080},"model":"item/jungle_pressure_plate"},
{"predicate":{"custom_model_data":53721081},"model":"item/light_blue_terracotta"},
{"predicate":{"custom_model_data":53721082},"model":"item/light_gray_terracotta"},
{"predicate":{"custom_model_data":53721083},"model":"item/magenta_stained_glass"},
{"predicate":{"custom_model_data":53721084},"model":"item/mangrove_hanging_sign"},
{"predicate":{"custom_model_data":53721085},"model":"item/pearlescent_froglight"},
{"predicate":{"custom_model_data":53721086},"model":"item/polished_diorite_slab"},
{"predicate":{"custom_model_data":53721087},"model":"item/polished_granite_slab"},
{"predicate":{"custom_model_data":53721088},"model":"item/prismarine_brick_slab"},
{"predicate":{"custom_model_data":53721089},"model":"item/red_glazed_terracotta"},
{"predicate":{"custom_model_data":53721090},"model":"item/red_nether_brick_slab"},
{"predicate":{"custom_model_data":53721091},"model":"item/red_nether_brick_wall"},
{"predicate":{"custom_model_data":53721092},"model":"item/shelter_pottery_sherd"},
{"predicate":{"custom_model_data":53721093},"model":"item/smooth_sandstone_slab"},
{"predicate":{"custom_model_data":53721094},"model":"item/spruce_pressure_plate"},
{"predicate":{"custom_model_data":53721095},"model":"item/stripped_bamboo_block"},
{"predicate":{"custom_model_data":53721096},"model":"item/stripped_crimson_stem"},
{"predicate":{"custom_model_data":53721097},"model":"item/stripped_dark_oak_log"},
{"predicate":{"custom_model_data":53721098},"model":"item/stripped_mangrove_log"},
{"predicate":{"custom_model_data":53721099},"model":"item/warped_pressure_plate"},
{"predicate":{"custom_model_data":53721100},"model":"item/waxed_cut_copper_slab"},
{"predicate":{"custom_model_data":53721101},"model":"item/waxed_oxidized_copper"},
{"predicate":{"custom_model_data":53721102},"model":"item/white_concrete_powder"},
{"predicate":{"custom_model_data":53721103},"model":"item/wither_skeleton_skull"},
{"predicate":{"custom_model_data":53721104},"model":"item/flowering_azalea_leaves"},
{"predicate":{"custom_model_data":53721105},"model":"item/command_block_minecart"},
{"predicate":{"custom_model_data":53721106},"model":"item/enchanted_golden_apple"},
{"predicate":{"custom_model_data":53721107},"model":"item/explorer_pottery_sherd"},
{"predicate":{"custom_model_data":53721108},"model":"item/glistering_melon_slice"},
{"predicate":{"custom_model_data":53721109},"model":"item/piglin_brute_spawn_egg"},
{"predicate":{"custom_model_data":53721110},"model":"item/blue_glazed_terracotta"},
{"predicate":{"custom_model_data":53721111},"model":"item/chiseled_nether_bricks"},
{"predicate":{"custom_model_data":53721112},"model":"item/chiseled_red_sandstone"},
{"predicate":{"custom_model_data":53721113},"model":"item/cobbled_deepslate_slab"},
{"predicate":{"custom_model_data":53721114},"model":"item/cobbled_deepslate_wall"},
{"predicate":{"custom_model_data":53721115},"model":"item/creeper_banner_pattern"},
{"predicate":{"custom_model_data":53721116},"model":"item/crimson_pressure_plate"},
{"predicate":{"custom_model_data":53721117},"model":"item/cut_red_sandstone_slab"},
{"predicate":{"custom_model_data":53721118},"model":"item/cyan_glazed_terracotta"},
{"predicate":{"custom_model_data":53721119},"model":"item/dark_prismarine_stairs"},
{"predicate":{"custom_model_data":53721120},"model":"item/dead_brain_coral_block"},
{"predicate":{"custom_model_data":53721121},"model":"item/deepslate_brick_stairs"},
{"predicate":{"custom_model_data":53721122},"model":"item/deepslate_redstone_ore"},
{"predicate":{"custom_model_data":53721123},"model":"item/end_stone_brick_stairs"},
{"predicate":{"custom_model_data":53721124},"model":"item/ender_dragon_spawn_egg"},
{"predicate":{"custom_model_data":53721125},"model":"item/gray_glazed_terracotta"},
{"predicate":{"custom_model_data":53721126},"model":"item/light_blue_shulker_box"},
{"predicate":{"custom_model_data":53721127},"model":"item/light_gray_shulker_box"},
{"predicate":{"custom_model_data":53721128},"model":"item/lime_glazed_terracotta"},
{"predicate":{"custom_model_data":53721129},"model":"item/mossy_cobblestone_slab"},
{"predicate":{"custom_model_data":53721130},"model":"item/mossy_cobblestone_wall"},
{"predicate":{"custom_model_data":53721131},"model":"item/mossy_stone_brick_slab"},
{"predicate":{"custom_model_data":53721132},"model":"item/mossy_stone_brick_wall"},
{"predicate":{"custom_model_data":53721133},"model":"item/orange_concrete_powder"},
{"predicate":{"custom_model_data":53721134},"model":"item/pink_glazed_terracotta"},
{"predicate":{"custom_model_data":53721135},"model":"item/polished_andesite_slab"},
{"predicate":{"custom_model_data":53721136},"model":"item/purple_concrete_powder"},
{"predicate":{"custom_model_data":53721137},"model":"item/red_stained_glass_pane"},
{"predicate":{"custom_model_data":53721138},"model":"item/trader_llama_spawn_egg"},
{"predicate":{"custom_model_data":53721139},"model":"item/zombie_horse_spawn_egg"},
{"predicate":{"custom_model_data":53721140},"model":"item/stripped_dark_oak_wood"},
{"predicate":{"custom_model_data":53721141},"model":"item/stripped_mangrove_wood"},
{"predicate":{"custom_model_data":53721142},"model":"item/stripped_warped_hyphae"},
{"predicate":{"custom_model_data":53721143},"model":"item/waxed_weathered_copper"},
{"predicate":{"custom_model_data":53721144},"model":"item/yellow_concrete_powder"},
{"predicate":{"custom_model_data":53721145},"model":"item/black_glazed_terracotta"},
{"predicate":{"custom_model_data":53721146},"model":"item/blue_stained_glass_pane"},
{"predicate":{"custom_model_data":53721147},"model":"item/brown_glazed_terracotta"},
{"predicate":{"custom_model_data":53721148},"model":"item/calibrated_sculk_sensor"},
{"predicate":{"custom_model_data":53721149},"model":"item/cracked_deepslate_tiles"},
{"predicate":{"custom_model_data":53721150},"model":"item/cyan_stained_glass_pane"},
{"predicate":{"custom_model_data":53721151},"model":"item/dark_oak_pressure_plate"},
{"predicate":{"custom_model_data":53721152},"model":"item/dead_bubble_coral_block"},
{"predicate":{"custom_model_data":53721153},"model":"item/exposed_cut_copper_slab"},
{"predicate":{"custom_model_data":53721154},"model":"item/gray_stained_glass_pane"},
{"predicate":{"custom_model_data":53721155},"model":"item/green_glazed_terracotta"},
{"predicate":{"custom_model_data":53721156},"model":"item/lime_stained_glass_pane"},
{"predicate":{"custom_model_data":53721157},"model":"item/magenta_concrete_powder"},
{"predicate":{"custom_model_data":53721158},"model":"item/mangrove_pressure_plate"},
{"predicate":{"custom_model_data":53721159},"model":"item/pink_stained_glass_pane"},
{"predicate":{"custom_model_data":53721160},"model":"item/polished_deepslate_slab"},
{"predicate":{"custom_model_data":53721161},"model":"item/polished_deepslate_wall"},
{"predicate":{"custom_model_data":53721162},"model":"item/polished_diorite_stairs"},
{"predicate":{"custom_model_data":53721163},"model":"item/polished_granite_stairs"},
{"predicate":{"custom_model_data":53721164},"model":"item/prismarine_brick_stairs"},
{"predicate":{"custom_model_data":53721165},"model":"item/red_nether_brick_stairs"},
{"predicate":{"custom_model_data":53721166},"model":"item/repeating_command_block"},
{"predicate":{"custom_model_data":53721167},"model":"item/tropical_fish_spawn_egg"},
{"predicate":{"custom_model_data":53721168},"model":"item/smooth_sandstone_stairs"},
{"predicate":{"custom_model_data":53721169},"model":"item/stripped_crimson_hyphae"},
{"predicate":{"custom_model_data":53721170},"model":"item/waxed_cut_copper_stairs"},
{"predicate":{"custom_model_data":53721171},"model":"item/white_glazed_terracotta"},
{"predicate":{"custom_model_data":53721172},"model":"item/elder_guardian_spawn_egg"},
{"predicate":{"custom_model_data":53721173},"model":"item/heartbreak_pottery_sherd"},
{"predicate":{"custom_model_data":53721174},"model":"item/black_stained_glass_pane"},
{"predicate":{"custom_model_data":53721175},"model":"item/brown_stained_glass_pane"},
{"predicate":{"custom_model_data":53721176},"model":"item/cobbled_deepslate_stairs"},
{"predicate":{"custom_model_data":53721177},"model":"item/cracked_deepslate_bricks"},
{"predicate":{"custom_model_data":53721178},"model":"item/green_stained_glass_pane"},
{"predicate":{"custom_model_data":53721179},"model":"item/light_blue_stained_glass"},
{"predicate":{"custom_model_data":53721180},"model":"item/light_gray_stained_glass"},
{"predicate":{"custom_model_data":53721181},"model":"item/mossy_cobblestone_stairs"},
{"predicate":{"custom_model_data":53721182},"model":"item/mossy_stone_brick_stairs"},
{"predicate":{"custom_model_data":53721183},"model":"item/orange_glazed_terracotta"},
{"predicate":{"custom_model_data":53721184},"model":"item/oxidized_cut_copper_slab"},
{"predicate":{"custom_model_data":53721185},"model":"item/polished_andesite_stairs"},
{"predicate":{"custom_model_data":53721186},"model":"item/polished_blackstone_slab"},
{"predicate":{"custom_model_data":53721187},"model":"item/polished_blackstone_wall"},
{"predicate":{"custom_model_data":53721188},"model":"item/purple_glazed_terracotta"},
{"predicate":{"custom_model_data":53721189},"model":"item/skeleton_horse_spawn_egg"},
{"predicate":{"custom_model_data":53721190},"model":"item/warped_fungus_on_a_stick"},
{"predicate":{"custom_model_data":53721191},"model":"item/waxed_exposed_cut_copper"},
{"predicate":{"custom_model_data":53721192},"model":"item/white_stained_glass_pane"},
{"predicate":{"custom_model_data":53721193},"model":"item/yellow_glazed_terracotta"},
{"predicate":{"custom_model_data":53721194},"model":"item/exposed_cut_copper_stairs"},
{"predicate":{"custom_model_data":53721195},"model":"item/magenta_glazed_terracotta"},
{"predicate":{"custom_model_data":53721196},"model":"item/orange_stained_glass_pane"},
{"predicate":{"custom_model_data":53721197},"model":"item/polished_deepslate_stairs"},
{"predicate":{"custom_model_data":53721198},"model":"item/purple_stained_glass_pane"},
{"predicate":{"custom_model_data":53721199},"model":"item/wither_skeleton_spawn_egg"},
{"predicate":{"custom_model_data":53721200},"model":"item/zombie_villager_spawn_egg"},
{"predicate":{"custom_model_data":53721201},"model":"item/smooth_red_sandstone_slab"},
{"predicate":{"custom_model_data":53721202},"model":"item/waxed_oxidized_cut_copper"},
{"predicate":{"custom_model_data":53721203},"model":"item/weathered_cut_copper_slab"},
{"predicate":{"custom_model_data":53721204},"model":"item/yellow_stained_glass_pane"},
{"predicate":{"custom_model_data":53721205},"model":"item/light_blue_concrete_powder"},
{"predicate":{"custom_model_data":53721206},"model":"item/light_gray_concrete_powder"},
{"predicate":{"custom_model_data":53721207},"model":"item/magenta_stained_glass_pane"},
{"predicate":{"custom_model_data":53721208},"model":"item/oxidized_cut_copper_stairs"},
{"predicate":{"custom_model_data":53721209},"model":"item/polished_blackstone_bricks"},
{"predicate":{"custom_model_data":53721210},"model":"item/polished_blackstone_button"},
{"predicate":{"custom_model_data":53721211},"model":"item/polished_blackstone_stairs"},
{"predicate":{"custom_model_data":53721212},"model":"item/wandering_trader_spawn_egg"},
{"predicate":{"custom_model_data":53721213},"model":"item/zombified_piglin_spawn_egg"},
{"predicate":{"custom_model_data":53721214},"model":"item/waxed_weathered_cut_copper"},
{"predicate":{"custom_model_data":53721215},"model":"item/infested_mossy_stone_bricks"},
{"predicate":{"custom_model_data":53721216},"model":"item/smooth_red_sandstone_stairs"},
{"predicate":{"custom_model_data":53721217},"model":"item/weathered_cut_copper_stairs"},
{"predicate":{"custom_model_data":53721218},"model":"item/chiseled_polished_blackstone"},
{"predicate":{"custom_model_data":53721219},"model":"item/light_blue_glazed_terracotta"},
{"predicate":{"custom_model_data":53721220},"model":"item/light_gray_glazed_terracotta"},
{"predicate":{"custom_model_data":53721221},"model":"item/heavy_weighted_pressure_plate"},
{"predicate":{"custom_model_data":53721222},"model":"item/infested_cracked_stone_bricks"},
{"predicate":{"custom_model_data":53721223},"model":"item/light_blue_stained_glass_pane"},
{"predicate":{"custom_model_data":53721224},"model":"item/light_gray_stained_glass_pane"},
{"predicate":{"custom_model_data":53721225},"model":"item/light_weighted_pressure_plate"},
{"predicate":{"custom_model_data":53721226},"model":"item/waxed_exposed_cut_copper_slab"},
{"predicate":{"custom_model_data":53721227},"model":"item/infested_chiseled_stone_bricks"},
{"predicate":{"custom_model_data":53721228},"model":"item/polished_blackstone_brick_slab"},
{"predicate":{"custom_model_data":53721229},"model":"item/polished_blackstone_brick_wall"},
{"predicate":{"custom_model_data":53721230},"model":"item/waxed_oxidized_cut_copper_slab"},
{"predicate":{"custom_model_data":53721231},"model":"item/waxed_exposed_cut_copper_stairs"},
{"predicate":{"custom_model_data":53721232},"model":"item/waxed_weathered_cut_copper_slab"},
{"predicate":{"custom_model_data":53721233},"model":"item/eye_armor_trim_smithing_template"},
{"predicate":{"custom_model_data":53721234},"model":"item/rib_armor_trim_smithing_template"},
{"predicate":{"custom_model_data":53721235},"model":"item/polished_blackstone_brick_stairs"},
{"predicate":{"custom_model_data":53721236},"model":"item/vex_armor_trim_smithing_template"},
{"predicate":{"custom_model_data":53721237},"model":"item/waxed_oxidized_cut_copper_stairs"},
{"predicate":{"custom_model_data":53721238},"model":"item/dune_armor_trim_smithing_template"},
{"predicate":{"custom_model_data":53721239},"model":"item/host_armor_trim_smithing_template"},
{"predicate":{"custom_model_data":53721240},"model":"item/tide_armor_trim_smithing_template"},
{"predicate":{"custom_model_data":53721241},"model":"item/ward_armor_trim_smithing_template"},
{"predicate":{"custom_model_data":53721242},"model":"item/wild_armor_trim_smithing_template"},
{"predicate":{"custom_model_data":53721243},"model":"item/waxed_weathered_cut_copper_stairs"},
{"predicate":{"custom_model_data":53721244},"model":"item/coast_armor_trim_smithing_template"},
{"predicate":{"custom_model_data":53721245},"model":"item/cracked_polished_blackstone_bricks"},
{"predicate":{"custom_model_data":53721246},"model":"item/polished_blackstone_pressure_plate"},
{"predicate":{"custom_model_data":53721247},"model":"item/snout_armor_trim_smithing_template"},
{"predicate":{"custom_model_data":53721248},"model":"item/spire_armor_trim_smithing_template"},
{"predicate":{"custom_model_data":53721249},"model":"item/netherite_upgrade_smithing_template"},
{"predicate":{"custom_model_data":53721250},"model":"item/raiser_armor_trim_smithing_template"},
{"predicate":{"custom_model_data":53721251},"model":"item/sentry_armor_trim_smithing_template"},
{"predicate":{"custom_model_data":53721252},"model":"item/silence_armor_trim_smithing_template"},
{"predicate":{"custom_model_data":53721253},"model":"item/shaper_armor_trim_smithing_template"},
{"predicate":{"custom_model_data":53721254},"model":"item/wayfinder_armor_trim_smithing_template"}
]
}

